{
  "title": "[EgyFilm] w3d ablys S01",
  "episodes": [
    {
      "name": "Episode 01",
      "url": "https://deva-cpmav9sk6x23.cimanowtv.com/uploads/2022/09/17/_Cima-Now.CoM_%20Wa3d.Ebles.S01E01.FHD/%5BCima-Now.CoM%5D%20Wa3d.Ebles.S01E01.FHD-720p.mp4",
      "size": "620.16 ميجا"
    },
    {
      "name": "Episode 02",
      "url": "https://deva-cpmav9sk6x23.cimanowtv.com/uploads/2022/09/18/_Cima-Now.CoM_%20Wa3d.Ebles.S01E02.FHD/%5BCima-Now.CoM%5D%20Wa3d.Ebles.S01E02.FHD-720p.mp4",
      "size": "596.88 ميجا"
    },
    {
      "name": "Episode 03",
      "url": "https://deva-cpmav9sk6x23.cimanowtv.com/uploads/2022/09/22/_Cima-Now.CoM_%20Wa3d.Ebles.S01E03.FHD/%5BCima-Now.CoM%5D%20Wa3d.Ebles.S01E03.FHD-720p.mp4",
      "size": "548.09 ميجا"
    },
    {
      "name": "Episode 04",
      "url": "https://deva-cpmav9sk6x23.cimanowtv.com/uploads/2022/09/29/_Cima-Now.CoM_%20Wa3d.Ebles.S01E04.FHD/%5BCima-Now.CoM%5D%20Wa3d.Ebles.S01E04.FHD-720p.mp4",
      "size": "533.51 ميجا"
    },
    {
      "name": "Episode 05",
      "url": "https://deva-cpmav9sk6x26.cimanowtv.com/uploads/2022/10/06/_Cima-Now.CoM_%20Wa3d.Ebles.S01E05.FHD/%5BCima-Now.CoM%5D%20Wa3d.Ebles.S01E05.FHD-720p.mp4",
      "size": "513.44 ميجا"
    },
    {
      "name": "Episode 06",
      "url": "https://deva-cpmav9sk6x25.cimanowtv.com/uploads/2022/10/14/_Cima-Now.CoM_%20Wa3d.Ebles.S01E06.FHD/%5BCima-Now.CoM%5D%20Wa3d.Ebles.S01E06.FHD-720p.mp4",
      "size": "484.88 ميجا"
    },
    {
      "name": "Episode 07",
      "url": "https://deva-cpmav9sk6x26.cimanowtv.com/uploads/2022/10/20/_Cima-Now.CoM_%20Om.El.Donia.S01E07.HD/%5BCima-Now.CoM%5D%20Om.El.Donia.S01E07.HD-720p.mp4",
      "size": "438.98 ميجا"
    },
    {
      "name": "Episode 08",
      "url": "https://deva-cpmav9sk6x26.cimanowtv.com/uploads/2022/10/20/_Cima-Now.CoM_%20Om.El.Donia.S01E08.HD/%5BCima-Now.CoM%5D%20Om.El.Donia.S01E08.HD-720p.mp4",
      "size": "409.41 ميجا"
    },
    {
      "name": "Episode 09",
      "url": "https://deva-cpmav9sk6x25.cimanowtv.com/uploads/2022/10/27/_Cima-Now.CoM_%20Om.El.Donia.S01E09.HD/%5BCima-Now.CoM%5D%20Om.El.Donia.S01E09.HD-720p.mp4",
      "size": "479.12 ميجا"
    },
    {
      "name": "Episode 10",
      "url": "https://deva-cpmav9sk6x26.cimanowtv.com/uploads/2022/10/27/_Cima-Now.CoM_%20Om.El.Donia.S01E10.HD/%5BCima-Now.CoM%5D%20Om.El.Donia.S01E10.HD-720p.mp4",
      "size": "426.36 ميجا"
    },
    {
      "name": "Episode 11",
      "url": "https://deva-cpmav9sk6x26.cimanowtv.com/uploads/2022/11/03/_Cima-Now.CoM_%20Om.El.Donia.S01E11.HD/%5BCima-Now.CoM%5D%20Om.El.Donia.S01E11.HD-720p.mp4",
      "size": "464.77 ميجا"
    },
    {
      "name": "Episode 12",
      "url": "https://deva-cpmav9sk6x25.cimanowtv.com/uploads/2022/11/03/_Cima-Now.CoM_%20Om.El.Donia.S01E12.HD/%5BCima-Now.CoM%5D%20Om.El.Donia.S01E12.HD-720p.mp4",
      "size": "338.78 ميجا"
    },
    {
      "name": "Episode 13",
      "url": "https://deva-cpmav9sk6x25.cimanowtv.com/uploads/2022/11/10/_Cima-Now.CoM_%20Om.El.Donia.S01E13.HD/%5BCima-Now.CoM%5D%20Om.El.Donia.S01E13.HD-720p.mp4",
      "size": "402.03 ميجا"
    },
    {
      "name": "Episode 14",
      "url": "https://deva-cpmav9sk6x25.cimanowtv.com/uploads/2022/11/10/_Cima-Now.CoM_%20Om.El.Donia.S01E14.HD/%5BCima-Now.CoM%5D%20Om.El.Donia.S01E14.HD-720p.mp4",
      "size": "445.92 ميجا"
    },
    {
      "name": "Episode 15",
      "url": "https://deva-cpmav9sk6x26.cimanowtv.com/uploads/2022/11/17/_Cima-Now.CoM_%20Om.El.Donia.S01E15.HD/%5BCima-Now.CoM%5D%20Om.El.Donia.S01E15.HD-720p.mp4",
      "size": "584.27 ميجا"
    }
  ]
}