{
  "title": "[EgyFilm] almshwar S01",
  "episodes": [
    {
      "name": "Episode 01",
      "url": "https://deva-cpmav9sk6x21.cimanowtv.com/uploads/2022/04/02/_Cima-Now.CoM_%20El.Meshwar.S01E01.HD/%5BCima-Now.CoM%5D%20El.Meshwar.S01E01.HD-1080p.mp4",
      "size": "779.94 ميجا"
    },
    {
      "name": "Episode 02",
      "url": "https://deva-cpmav9sk6x21.cimanowtv.com/uploads/2022/04/03/_Cima-Now.CoM_%20El.Meshwar.S01E02.HD/%5BCima-Now.CoM%5D%20El.Meshwar.S01E02.HD-1080p.mp4",
      "size": "642.55 ميجا"
    },
    {
      "name": "Episode 03",
      "url": "https://deva-cpmav9sk6x21.cimanowtv.com/uploads/2022/04/04/_Cima-Now.CoM_%20El.Meshwar.S01E03.HD/%5BCima-Now.CoM%5D%20El.Meshwar.S01E03.HD-1080p.mp4",
      "size": "550.94 ميجا"
    },
    {
      "name": "Episode 04",
      "url": "https://deva-cpmav9sk6x19.cimanowtv.com/uploads/2022/04/05/_Cima-Now.CoM_%20El.Meshwar.S01E04.HD/%5BCima-Now.CoM%5D%20El.Meshwar.S01E04.HD-1080p.mp4",
      "size": "572.62 ميجا"
    },
    {
      "name": "Episode 05",
      "url": "https://deva-cpmav9sk6x21.cimanowtv.com/uploads/2022/04/06/_Cima-Now.CoM_%20El.Meshwar.S01E05.HD/%5BCima-Now.CoM%5D%20El.Meshwar.S01E05.HD-1080p.mp4",
      "size": "525.54 ميجا"
    },
    {
      "name": "Episode 06",
      "url": "https://deva-cpmav9sk6x21.cimanowtv.com/uploads/2022/04/07/_Cima-Now.CoM_%20El.Meshwar.S01E06.HD/%5BCima-Now.CoM%5D%20El.Meshwar.S01E06.HD-1080p.mp4",
      "size": "505.09 ميجا"
    },
    {
      "name": "Episode 07",
      "url": "https://deva-cpmav9sk6x19.cimanowtv.com/uploads/2022/04/08/_Cima-Now.CoM_%20El.Meshwar.S01E07.HD/%5BCima-Now.CoM%5D%20El.Meshwar.S01E07.HD-1080p.mp4",
      "size": "430.82 ميجا"
    },
    {
      "name": "Episode 08",
      "url": "https://deva-cpmav9sk6x19.cimanowtv.com/uploads/2022/04/09/_Cima-Now.CoM_%20El.Meshwar.S01E08.HD/%5BCima-Now.CoM%5D%20El.Meshwar.S01E08.HD-1080p.mp4",
      "size": "497.89 ميجا"
    },
    {
      "name": "Episode 09",
      "url": "https://deva-cpmav9sk6x21.cimanowtv.com/uploads/2022/04/10/_Cima-Now.CoM_%20El.Meshwar.S01E09.HD/%5BCima-Now.CoM%5D%20El.Meshwar.S01E09.HD-1080p.mp4",
      "size": "503.48 ميجا"
    },
    {
      "name": "Episode 10",
      "url": "https://deva-cpmav9sk6x19.cimanowtv.com/uploads/2022/04/11/_Cima-Now.CoM_%20El.Meshwar.S01E10.HD/%5BCima-Now.CoM%5D%20El.Meshwar.S01E10.HD-1080p.mp4",
      "size": "582.33 ميجا"
    },
    {
      "name": "Episode 26",
      "url": "https://deva-cpmav9sk6x24.cimanowtv.com/uploads/2022/04/27/_Cima-Now.CoM_%20El.Meshwar.S01E26.HD/%5BCima-Now.CoM%5D%20El.Meshwar.S01E26.HD-1080p.mp4",
      "size": "527.04 ميجا"
    },
    {
      "name": "Episode 27",
      "url": "https://deva-cpmav9sk6x24.cimanowtv.com/uploads/2022/04/28/_Cima-Now.CoM_%20El.Meshwar.S01E27.HD/%5BCima-Now.CoM%5D%20El.Meshwar.S01E27.HD-1080p.mp4",
      "size": "531.25 ميجا"
    },
    {
      "name": "Episode 28",
      "url": "https://deva-cpmav9sk6x24.cimanowtv.com/uploads/2022/04/29/_Cima-Now.CoM_%20El.Meshwar.S01E28.HD/%5BCima-Now.CoM%5D%20El.Meshwar.S01E28.HD-1080p.mp4",
      "size": "558.51 ميجا"
    },
    {
      "name": "Episode 29",
      "url": "https://deva-cpmav9sk6x24.cimanowtv.com/uploads/2022/04/30/_Cima-Now.CoM_%20El.Meshwar.S01E29.HD/%5BCima-Now.CoM%5D%20El.Meshwar.S01E29.HD-1080p.mp4",
      "size": "494.50 ميجا"
    },
    {
      "name": "Episode 30",
      "url": "https://deva-cpmav9sk6x23.cimanowtv.com/uploads/2022/05/01/_Cima-Now.CoM_%20El.Meshwar.S01E30.HD/%5BCima-Now.CoM%5D%20El.Meshwar.S01E30.HD-1080p.mp4",
      "size": "839.01 ميجا"
    }
  ]
}