{
  "title": "[EgyFilm] mftr2 tr2 S01",
  "episodes": [
    {
      "name": "Episode 01",
      "url": "https://deva-cpmav9sk6x35.cimanowtv.com/uploads/2024/06/01/_Cima-Now.CoM_%20Moftaraq.Toroq.S01E01.HD/%5BCima-Now.CoM%5D%20Moftaraq.Toroq.S01E01.HD-1080p.mp4",
      "size": "853.43 ميجا"
    },
    {
      "name": "Episode 02",
      "url": "https://deva-cpmav9sk6x33.cimanowtv.com/uploads/2024/06/01/_Cima-Now.CoM_%20Moftaraq.Toroq.S01E02.HD/%5BCima-Now.CoM%5D%20Moftaraq.Toroq.S01E02.HD-1080p.mp4",
      "size": "762.25 ميجا"
    },
    {
      "name": "Episode 03",
      "url": "https://deva-cpmav9sk6x35.cimanowtv.com/uploads/2024/06/02/_Cima-Now.CoM_%20Moftaraq.Toroq.S01E03.HD/%5BCima-Now.CoM%5D%20Moftaraq.Toroq.S01E03.HD-1080p.mp4",
      "size": "710.72 ميجا"
    },
    {
      "name": "Episode 04",
      "url": "https://deva-cpmav9sk6x35.cimanowtv.com/uploads/2024/06/03/_Cima-Now.CoM_%20Moftaraq.Toroq.S01E04.HD/%5BCima-Now.CoM%5D%20Moftaraq.Toroq.S01E04.HD-1080p.mp4",
      "size": "759.26 ميجا"
    },
    {
      "name": "Episode 05",
      "url": "https://deva-cpmav9sk6x33.cimanowtv.com/uploads/2024/06/04/_Cima-Now.CoM_%20Moftaraq.Toroq.S01E05.HD/%5BCima-Now.CoM%5D%20Moftaraq.Toroq.S01E05.HD-1080p.mp4",
      "size": "725.93 ميجا"
    },
    {
      "name": "Episode 06",
      "url": "https://deva-cpmav9sk6x34.cimanowtv.com/uploads/2024/06/08/_Cima-Now.CoM_%20Moftaraq.Toroq.S01E06.HD/%5BCima-Now.CoM%5D%20Moftaraq.Toroq.S01E06.HD-1080p.mp4",
      "size": "783.31 ميجا"
    },
    {
      "name": "Episode 07",
      "url": "https://deva-cpmav9sk6x35.cimanowtv.com/uploads/2024/06/09/_Cima-Now.CoM_%20Moftaraq.Toroq.S01E07.HD/%5BCima-Now.CoM%5D%20Moftaraq.Toroq.S01E07.HD-1080p.mp4",
      "size": "797.71 ميجا"
    },
    {
      "name": "Episode 08",
      "url": "https://deva-cpmav9sk6x35.cimanowtv.com/uploads/2024/06/10/_Cima-Now.CoM_%20Moftaraq.Toroq.S01E08.HD/%5BCima-Now.CoM%5D%20Moftaraq.Toroq.S01E08.HD-1080p.mp4",
      "size": "608.84 ميجا"
    },
    {
      "name": "Episode 09",
      "url": "https://deva-cpmav9sk6x35.cimanowtv.com/uploads/2024/06/11/_Cima-Now.CoM_%20Moftaraq.Toroq.S01E09.HD/%5BCima-Now.CoM%5D%20Moftaraq.Toroq.S01E09.HD-1080p.mp4",
      "size": "734.09 ميجا"
    },
    {
      "name": "Episode 10",
      "url": "https://deva-cpmav9sk6x35.cimanowtv.com/uploads/2024/06/15/_Cima-Now.CoM_%20Moftaraq.Toroq.S01E10.HD/%5BCima-Now.CoM%5D%20Moftaraq.Toroq.S01E10.HD-1080p.mp4",
      "size": "645.04 ميجا"
    },
    {
      "name": "Episode 11",
      "url": "https://deva-cpmav9sk6x35.cimanowtv.com/uploads/2024/06/16/_Cima-Now.CoM_%20Moftaraq.Toroq.S01E11.HD/%5BCima-Now.CoM%5D%20Moftaraq.Toroq.S01E11.HD-1080p.mp4",
      "size": "643.25 ميجا"
    },
    {
      "name": "Episode 12",
      "url": "https://deva-cpmav9sk6x34.cimanowtv.com/uploads/2024/06/17/_Cima-Now.CoM_%20Moftaraq.Toroq.S01E12.HD/%5BCima-Now.CoM%5D%20Moftaraq.Toroq.S01E12.HD-1080p.mp4",
      "size": "600.35 ميجا"
    },
    {
      "name": "Episode 13",
      "url": "https://deva-cpmav9sk6x33.cimanowtv.com/uploads/2024/06/18/_Cima-Now.CoM_%20Moftaraq.Toroq.S01E13.HD/%5BCima-Now.CoM%5D%20Moftaraq.Toroq.S01E13.HD-1080p.mp4",
      "size": "658.57 ميجا"
    },
    {
      "name": "Episode 14",
      "url": "https://deva-cpmav9sk6x33.cimanowtv.com/uploads/2024/06/22/_Cima-Now.CoM_%20Moftaraq.Toroq.S01E14.HD/%5BCima-Now.CoM%5D%20Moftaraq.Toroq.S01E14.HD-1080p.mp4",
      "size": "607.31 ميجا"
    },
    {
      "name": "Episode 15",
      "url": "https://deva-cpmav9sk6x33.cimanowtv.com/uploads/2024/06/23/_Cima-Now.CoM_%20Moftaraq.Toroq.S01E15.HD/%5BCima-Now.CoM%5D%20Moftaraq.Toroq.S01E15.HD-1080p.mp4",
      "size": "690.66 ميجا"
    },
    {
      "name": "Episode 16",
      "url": "https://deva-cpmav9sk6x35.cimanowtv.com/uploads/2024/06/24/_Cima-Now.CoM_%20Moftaraq.Toroq.S01E16.HD/%5BCima-Now.CoM%5D%20Moftaraq.Toroq.S01E16.HD-1080p.mp4",
      "size": "736.26 ميجا"
    },
    {
      "name": "Episode 17",
      "url": "https://deva-cpmav9sk6x35.cimanowtv.com/uploads/2024/06/25/_Cima-Now.CoM_%20Moftaraq.Toroq.S01E17.HD/%5BCima-Now.CoM%5D%20Moftaraq.Toroq.S01E17.HD-1080p.mp4",
      "size": "660.12 ميجا"
    },
    {
      "name": "Episode 18",
      "url": "https://deva-cpmav9sk6x35.cimanowtv.com/uploads/2024/06/29/_Cima-Now.CoM_%20Moftaraq.Toroq.S01E18.HD/%5BCima-Now.CoM%5D%20Moftaraq.Toroq.S01E18.HD-1080p.mp4",
      "size": "703.59 ميجا"
    },
    {
      "name": "Episode 19",
      "url": "https://deva-cpmav9sk6x33.cimanowtv.com/uploads/2024/06/30/_Cima-Now.CoM_%20Moftaraq.Toroq.S01E19.HD/%5BCima-Now.CoM%5D%20Moftaraq.Toroq.S01E19.HD-1080p.mp4",
      "size": "718.06 ميجا"
    },
    {
      "name": "Episode 20",
      "url": "https://deva-cpmav9sk6x35.cimanowtv.com/uploads/2024/07/01/_Cima-Now.CoM_%20Moftaraq.Toroq.S01E20.HD/%5BCima-Now.CoM%5D%20Moftaraq.Toroq.S01E20.HD-1080p.mp4",
      "size": "692.20 ميجا"
    },
    {
      "name": "Episode 21",
      "url": "https://deva-cpmav9sk6x33.cimanowtv.com/uploads/2024/07/02/_Cima-Now.CoM_%20Moftaraq.Toroq.S01E21.HD/%5BCima-Now.CoM%5D%20Moftaraq.Toroq.S01E21.HD-1080p.mp4",
      "size": "593.87 ميجا"
    },
    {
      "name": "Episode 22",
      "url": "https://deva-cpmav9sk6x35.cimanowtv.com/uploads/2024/07/06/_Cima-Now.CoM_%20Moftaraq.Toroq.S01E22.HD/%5BCima-Now.CoM%5D%20Moftaraq.Toroq.S01E22.HD-1080p.mp4",
      "size": "634.37 ميجا"
    },
    {
      "name": "Episode 23",
      "url": "https://deva-cpmav9sk6x34.cimanowtv.com/uploads/2024/07/07/_Cima-Now.CoM_%20Moftaraq.Toroq.S01E23.HD/%5BCima-Now.CoM%5D%20Moftaraq.Toroq.S01E23.HD-1080p.mp4",
      "size": "665.20 ميجا"
    },
    {
      "name": "Episode 24",
      "url": "https://deva-cpmav9sk6x33.cimanowtv.com/uploads/2024/07/08/_Cima-Now.CoM_%20Moftaraq.Toroq.S01E24.HD/%5BCima-Now.CoM%5D%20Moftaraq.Toroq.S01E24.HD-1080p.mp4",
      "size": "665.95 ميجا"
    },
    {
      "name": "Episode 25",
      "url": "https://deva-cpmav9sk6x33.cimanowtv.com/uploads/2024/07/09/_Cima-Now.CoM_%20Moftaraq.Toroq.S01E25.HD/%5BCima-Now.CoM%5D%20Moftaraq.Toroq.S01E25.HD-1080p.mp4",
      "size": "665.74 ميجا"
    },
    {
      "name": "Episode 26",
      "url": "https://deva-cpmav9sk6x35.cimanowtv.com/uploads/2024/07/13/_Cima-Now.CoM_%20Moftaraq.Toroq.S01E26.HD/%5BCima-Now.CoM%5D%20Moftaraq.Toroq.S01E26.HD-1080p.mp4",
      "size": "725.20 ميجا"
    },
    {
      "name": "Episode 27",
      "url": "https://deva-cpmav9sk6x35.cimanowtv.com/uploads/2024/07/14/_Cima-Now.CoM_%20Moftaraq.Toroq.S01E27.HD/%5BCima-Now.CoM%5D%20Moftaraq.Toroq.S01E27.HD-1080p.mp4",
      "size": "744.65 ميجا"
    },
    {
      "name": "Episode 28",
      "url": "https://deva-cpmav9sk6x35.cimanowtv.com/uploads/2024/07/15/_Cima-Now.CoM_%20Moftaraq.Toroq.S01E28.HD/%5BCima-Now.CoM%5D%20Moftaraq.Toroq.S01E28.HD-1080p.mp4",
      "size": "667.85 ميجا"
    },
    {
      "name": "Episode 29",
      "url": "https://deva-cpmav9sk6x35.cimanowtv.com/uploads/2024/07/16/_Cima-Now.CoM_%20Moftaraq.Toroq.S01E29.HD/%5BCima-Now.CoM%5D%20Moftaraq.Toroq.S01E29.HD-1080p.mp4",
      "size": "618.75 ميجا"
    },
    {
      "name": "Episode 30",
      "url": "https://deva-cpmav9sk6x33.cimanowtv.com/uploads/2024/07/20/_Cima-Now.CoM_%20Moftaraq.Toroq.S01E30.HD/%5BCima-Now.CoM%5D%20Moftaraq.Toroq.S01E30.HD-1080p.mp4",
      "size": "669.73 ميجا"
    },
    {
      "name": "Episode 31",
      "url": "https://deva-cpmav9sk6x35.cimanowtv.com/uploads/2024/07/21/_Cima-Now.CoM_%20Moftaraq.Toroq.S01E31.HD/%5BCima-Now.CoM%5D%20Moftaraq.Toroq.S01E31.HD-1080p.mp4",
      "size": "567.49 ميجا"
    },
    {
      "name": "Episode 32",
      "url": "https://deva-cpmav9sk6x35.cimanowtv.com/uploads/2024/07/22/_Cima-Now.CoM_%20Moftaraq.Toroq.S01E32.HD/%5BCima-Now.CoM%5D%20Moftaraq.Toroq.S01E32.HD-1080p.mp4",
      "size": "599.50 ميجا"
    },
    {
      "name": "Episode 33",
      "url": "https://deva-cpmav9sk6x35.cimanowtv.com/uploads/2024/07/23/_Cima-Now.CoM_%20Moftaraq.Toroq.S01E33.HD/%5BCima-Now.CoM%5D%20Moftaraq.Toroq.S01E33.HD-1080p.mp4",
      "size": "665.73 ميجا"
    },
    {
      "name": "Episode 34",
      "url": "https://deva-cpmav9sk6x35.cimanowtv.com/uploads/2024/07/27/_Cima-Now.CoM_%20Moftaraq.Toroq.S01E34.HD/%5BCima-Now.CoM%5D%20Moftaraq.Toroq.S01E34.HD-1080p.mp4",
      "size": "633.20 ميجا"
    },
    {
      "name": "Episode 35",
      "url": "https://deva-cpmav9sk6x35.cimanowtv.com/uploads/2024/07/28/_Cima-Now.CoM_%20Moftaraq.Toroq.S01E35.HD/%5BCima-Now.CoM%5D%20Moftaraq.Toroq.S01E35.HD-1080p.mp4",
      "size": "806.44 ميجا"
    },
    {
      "name": "Episode 36",
      "url": "https://deva-cpmav9sk6x34.cimanowtv.com/uploads/2024/07/29/_Cima-Now.CoM_%20Moftaraq.Toroq.S01E36.HD/%5BCima-Now.CoM%5D%20Moftaraq.Toroq.S01E36.HD-1080p.mp4",
      "size": "698.38 ميجا"
    },
    {
      "name": "Episode 37",
      "url": "https://deva-cpmav9sk6x35.cimanowtv.com/uploads/2024/07/30/_Cima-Now.CoM_%20Moftaraq.Toroq.S01E37.HD/%5BCima-Now.CoM%5D%20Moftaraq.Toroq.S01E37.HD-1080p.mp4",
      "size": "732.16 ميجا"
    },
    {
      "name": "Episode 38",
      "url": "https://deva-cpmav9sk6x33.cimanowtv.com/uploads/2024/08/03/_Cima-Now.CoM_%20Moftaraq.Toroq.S01E38.HD/%5BCima-Now.CoM%5D%20Moftaraq.Toroq.S01E38.HD-1080p.mp4",
      "size": "676.99 ميجا"
    },
    {
      "name": "Episode 39",
      "url": "https://deva-cpmav9sk6x33.cimanowtv.com/uploads/2024/08/04/_Cima-Now.CoM_%20Moftaraq.Toroq.S01E39.HD/%5BCima-Now.CoM%5D%20Moftaraq.Toroq.S01E39.HD-1080p.mp4",
      "size": "790.27 ميجا"
    },
    {
      "name": "Episode 40",
      "url": "https://deva-cpmav9sk6x35.cimanowtv.com/uploads/2024/08/05/_Cima-Now.CoM_%20Moftaraq.Toroq.S01E40.HD/%5BCima-Now.CoM%5D%20Moftaraq.Toroq.S01E40.HD-1080p.mp4",
      "size": "657.26 ميجا"
    },
    {
      "name": "Episode 41",
      "url": "https://deva-cpmav9sk6x35.cimanowtv.com/uploads/2024/08/06/_Cima-Now.CoM_%20Moftaraq.Toroq.S01E41.HD/%5BCima-Now.CoM%5D%20Moftaraq.Toroq.S01E41.HD-1080p.mp4",
      "size": "681.43 ميجا"
    },
    {
      "name": "Episode 42",
      "url": "https://deva-cpmav9sk6x35.cimanowtv.com/uploads/2024/08/10/_Cima-Now.CoM_%20Moftaraq.Toroq.S01E42.HD/%5BCima-Now.CoM%5D%20Moftaraq.Toroq.S01E42.HD-1080p.mp4",
      "size": "680.66 ميجا"
    },
    {
      "name": "Episode 43",
      "url": "https://deva-cpmav9sk6x34.cimanowtv.com/uploads/2024/08/11/_Cima-Now.CoM_%20Moftaraq.Toroq.S01E43.HD/%5BCima-Now.CoM%5D%20Moftaraq.Toroq.S01E43.HD-1080p.mp4",
      "size": "797.91 ميجا"
    },
    {
      "name": "Episode 44",
      "url": "https://deva-cpmav9sk6x35.cimanowtv.com/uploads/2024/08/12/_Cima-Now.CoM_%20Moftaraq.Toroq.S01E44.HD/%5BCima-Now.CoM%5D%20Moftaraq.Toroq.S01E44.HD-1080p.mp4",
      "size": "708.29 ميجا"
    },
    {
      "name": "Episode 45",
      "url": "https://deva-cpmav9sk6x34.cimanowtv.com/uploads/2024/08/13/_Cima-Now.CoM_%20Moftaraq.Toroq.S01E45.HD/%5BCima-Now.CoM%5D%20Moftaraq.Toroq.S01E45.HD-1080p.mp4",
      "size": "983.15 ميجا"
    }
  ]
}