{
  "title": "[EgyFilm] al7lm S01",
  "episodes": [
    {
      "name": "Episode 01",
      "url": "https://deva-cpmav9sk6x19.cimanowtv.com/uploads/2022/01/03/_Cima-Now.CoM_%20El.7elm.S01E01.HD/%5BCima-Now.CoM%5D%20El.7elm.S01E01.HD-480p.mp4",
      "size": "295.07 ميجا"
    },
    {
      "name": "Episode 02",
      "url": "https://deva-cpmav9sk6x21.cimanowtv.com/uploads/2022/01/03/_Cima-Now.CoM_%20El.7elm.S01E02.HD/%5BCima-Now.CoM%5D%20El.7elm.S01E02.HD-480p.mp4",
      "size": "266.89 ميجا"
    },
    {
      "name": "Episode 03",
      "url": "https://deva-cpmav9sk6x21.cimanowtv.com/uploads/2022/01/03/_Cima-Now.CoM_%20El.7elm.S01E03.HD/%5BCima-Now.CoM%5D%20El.7elm.S01E03.HD-480p.mp4",
      "size": "209.87 ميجا"
    },
    {
      "name": "Episode 04",
      "url": "https://deva-cpmav9sk6x20.cimanowtv.com/uploads/2022/01/04/_Cima-Now.CoM_%20El.7elm.S01E04.HD/%5BCima-Now.CoM%5D%20El.7elm.S01E04.HD-480p.mp4",
      "size": "238.64 ميجا"
    },
    {
      "name": "Episode 05",
      "url": "https://deva-cpmav9sk6x20.cimanowtv.com/uploads/2022/01/05/_Cima-Now.CoM_%20El.7elm.S01E05.HD/%5BCima-Now.CoM%5D%20El.7elm.S01E05.HD-480p.mp4",
      "size": "240.01 ميجا"
    },
    {
      "name": "Episode 06",
      "url": "https://deva-cpmav9sk6x20.cimanowtv.com/uploads/2022/01/08/_Cima-Now.CoM_%20El.7elm.S01E06.HD/%5BCima-Now.CoM%5D%20El.7elm.S01E06.HD-480p.mp4",
      "size": "230.45 ميجا"
    },
    {
      "name": "Episode 07",
      "url": "https://deva-cpmav9sk6x21.cimanowtv.com/uploads/2022/01/09/_Cima-Now.CoM_%20El.7elm.S01E07.HD/%5BCima-Now.CoM%5D%20El.7elm.S01E07.HD-480p.mp4",
      "size": "233.14 ميجا"
    },
    {
      "name": "Episode 08",
      "url": "https://deva-cpmav9sk6x19.cimanowtv.com/uploads/2022/01/10/_Cima-Now.CoM_%20El.7elm.S01E08.HD/%5BCima-Now.CoM%5D%20El.7elm.S01E08.HD-480p.mp4",
      "size": "207.56 ميجا"
    },
    {
      "name": "Episode 09",
      "url": "https://deva-cpmav9sk6x20.cimanowtv.com/uploads/2022/01/11/_Cima-Now.CoM_%20El.7elm.S01E09.HD/%5BCima-Now.CoM%5D%20El.7elm.S01E09.HD-480p.mp4",
      "size": "230.62 ميجا"
    },
    {
      "name": "Episode 10",
      "url": "https://deva-cpmav9sk6x20.cimanowtv.com/uploads/2022/01/12/_Cima-Now.CoM_%20El.7elm.S01E10.HD/%5BCima-Now.CoM%5D%20El.7elm.S01E10.HD-480p.mp4",
      "size": "228.71 ميجا"
    },
    {
      "name": "Episode 11",
      "url": "https://deva-cpmav9sk6x20.cimanowtv.com/uploads/2022/01/15/_Cima-Now.CoM_%20El.7elm.S01E11.HD/%5BCima-Now.CoM%5D%20El.7elm.S01E11.HD-480p.mp4",
      "size": "228.17 ميجا"
    },
    {
      "name": "Episode 12",
      "url": "https://deva-cpmav9sk6x21.cimanowtv.com/uploads/2022/01/16/_Cima-Now.CoM_%20El.7elm.S01E12.HD/%5BCima-Now.CoM%5D%20El.7elm.S01E12.HD-480p.mp4",
      "size": "231.72 ميجا"
    },
    {
      "name": "Episode 13",
      "url": "https://deva-cpmav9sk6x21.cimanowtv.com/uploads/2022/01/17/_Cima-Now.CoM_%20El.7elm.S01E13.HD/%5BCima-Now.CoM%5D%20El.7elm.S01E13.HD-480p.mp4",
      "size": "227.39 ميجا"
    },
    {
      "name": "Episode 14",
      "url": "https://deva-cpmav9sk6x19.cimanowtv.com/uploads/2022/01/18/_Cima-Now.CoM_%20El.7elm.S01E14.HD/%5BCima-Now.CoM%5D%20El.7elm.S01E14.HD-480p.mp4",
      "size": "236.28 ميجا"
    },
    {
      "name": "Episode 15",
      "url": "https://deva-cpmav9sk6x20.cimanowtv.com/uploads/2022/01/19/_Cima-Now.CoM_%20El.7elm.S01E15.HD/%5BCima-Now.CoM%5D%20El.7elm.S01E15.HD-480p.mp4",
      "size": "217.70 ميجا"
    },
    {
      "name": "Episode 16",
      "url": "https://deva-cpmav9sk6x19.cimanowtv.com/uploads/2022/01/22/_Cima-Now.CoM_%20El.7elm.S01E16.HD/%5BCima-Now.CoM%5D%20El.7elm.S01E16.HD-480p.mp4",
      "size": "220.01 ميجا"
    },
    {
      "name": "Episode 17",
      "url": "https://deva-cpmav9sk6x20.cimanowtv.com/uploads/2022/01/23/_Cima-Now.CoM_%20El.7elm.S01E17.HD/%5BCima-Now.CoM%5D%20El.7elm.S01E17.HD-480p.mp4",
      "size": "218.82 ميجا"
    },
    {
      "name": "Episode 18",
      "url": "https://deva-cpmav9sk6x19.cimanowtv.com/uploads/2022/01/24/_Cima-Now.CoM_%20El.7elm.S01E18.HD/%5BCima-Now.CoM%5D%20El.7elm.S01E18.HD-480p.mp4",
      "size": "212.45 ميجا"
    },
    {
      "name": "Episode 19",
      "url": "https://deva-cpmav9sk6x21.cimanowtv.com/uploads/2022/01/26/_Cima-Now.CoM_%20El.7elm.S01E19.HD/%5BCima-Now.CoM%5D%20El.7elm.S01E19.HD-480p.mp4",
      "size": "216.79 ميجا"
    },
    {
      "name": "Episode 20",
      "url": "https://deva-cpmav9sk6x20.cimanowtv.com/uploads/2022/01/26/_Cima-Now.CoM_%20El.7elm.S01E20.HD/%5BCima-Now.CoM%5D%20El.7elm.S01E20.HD-480p.mp4",
      "size": "217.27 ميجا"
    },
    {
      "name": "Episode 21",
      "url": "https://deva-cpmav9sk6x20.cimanowtv.com/uploads/2022/01/29/_Cima-Now.CoM_%20El.7elm.S01E21.HD/%5BCima-Now.CoM%5D%20El.7elm.S01E21.HD-480p.mp4",
      "size": "226.21 ميجا"
    },
    {
      "name": "Episode 22",
      "url": "https://deva-cpmav9sk6x20.cimanowtv.com/uploads/2022/01/30/_Cima-Now.CoM_%20El.7elm.S01E22.HD/%5BCima-Now.CoM%5D%20El.7elm.S01E22.HD-480p.mp4",
      "size": "216.82 ميجا"
    },
    {
      "name": "Episode 23",
      "url": "https://deva-cpmav9sk6x19.cimanowtv.com/uploads/2022/01/31/_Cima-Now.CoM_%20El.7elm.S01E23.HD/%5BCima-Now.CoM%5D%20El.7elm.S01E23.HD-480p.mp4",
      "size": "216.71 ميجا"
    },
    {
      "name": "Episode 24",
      "url": "https://deva-cpmav9sk6x19.cimanowtv.com/uploads/2022/02/01/_Cima-Now.CoM_%20El.7elm.S01E24.HD/%5BCima-Now.CoM%5D%20El.7elm.S01E24.HD-480p.mp4",
      "size": "220.99 ميجا"
    },
    {
      "name": "Episode 25",
      "url": "https://deva-cpmav9sk6x19.cimanowtv.com/uploads/2022/02/02/_Cima-Now.CoM_%20El.7elm.S01E25.HD/%5BCima-Now.CoM%5D%20El.7elm.S01E25.HD-480p.mp4",
      "size": "214.86 ميجا"
    },
    {
      "name": "Episode 26",
      "url": "https://deva-cpmav9sk6x19.cimanowtv.com/uploads/2022/02/05/_Cima-Now.CoM_%20El.7elm.S01E26.HD/%5BCima-Now.CoM%5D%20El.7elm.S01E26.HD-480p.mp4",
      "size": "211.82 ميجا"
    },
    {
      "name": "Episode 27",
      "url": "https://deva-cpmav9sk6x19.cimanowtv.com/uploads/2022/02/06/_Cima-Now.CoM_%20El.7elm.S01E27.HD/%5BCima-Now.CoM%5D%20El.7elm.S01E27.HD-480p.mp4",
      "size": "215.45 ميجا"
    },
    {
      "name": "Episode 28",
      "url": "https://deva-cpmav9sk6x21.cimanowtv.com/uploads/2022/02/07/_Cima-Now.CoM_%20El.7elm.S01E28.HD/%5BCima-Now.CoM%5D%20El.7elm.S01E28.HD-480p.mp4",
      "size": "230.29 ميجا"
    },
    {
      "name": "Episode 29",
      "url": "https://deva-cpmav9sk6x19.cimanowtv.com/uploads/2022/02/08/_Cima-Now.CoM_%20El.7elm.S01E29.HD/%5BCima-Now.CoM%5D%20El.7elm.S01E29.HD-480p.mp4",
      "size": "189.42 ميجا"
    },
    {
      "name": "Episode 30",
      "url": "https://deva-cpmav9sk6x21.cimanowtv.com/uploads/2022/02/09/_Cima-Now.CoM_%20El.7elm.S01E30.HD/%5BCima-Now.CoM%5D%20El.7elm.S01E30.HD-480p.mp4",
      "size": "182.79 ميجا"
    },
    {
      "name": "Episode 31",
      "url": "https://deva-cpmav9sk6x20.cimanowtv.com/uploads/2022/02/12/_Cima-Now.CoM_%20El.7elm.S01E31.HD/%5BCima-Now.CoM%5D%20El.7elm.S01E31.HD-480p.mp4",
      "size": "209.66 ميجا"
    },
    {
      "name": "Episode 32",
      "url": "https://deva-cpmav9sk6x20.cimanowtv.com/uploads/2022/02/13/_Cima-Now.CoM_%20El.7elm.S01E32.HD/%5BCima-Now.CoM%5D%20El.7elm.S01E32.HD-480p.mp4",
      "size": "210.36 ميجا"
    },
    {
      "name": "Episode 33",
      "url": "https://deva-cpmav9sk6x19.cimanowtv.com/uploads/2022/02/14/_Cima-Now.CoM_%20El.7elm.S01E33.HD/%5BCima-Now.CoM%5D%20El.7elm.S01E33.HD-480p.mp4",
      "size": "196.48 ميجا"
    },
    {
      "name": "Episode 34",
      "url": "https://deva-cpmav9sk6x21.cimanowtv.com/uploads/2022/02/15/_Cima-Now.CoM_%20El.7elm.S01E34.HD/%5BCima-Now.CoM%5D%20El.7elm.S01E34.HD-480p.mp4",
      "size": "200.92 ميجا"
    },
    {
      "name": "Episode 35",
      "url": "https://deva-cpmav9sk6x21.cimanowtv.com/uploads/2022/02/16/_Cima-Now.CoM_%20El.7elm.S01E35.HD/%5BCima-Now.CoM%5D%20El.7elm.S01E35.HD-480p.mp4",
      "size": "197.59 ميجا"
    },
    {
      "name": "Episode 36",
      "url": "https://deva-cpmav9sk6x21.cimanowtv.com/uploads/2022/02/19/_Cima-Now.CoM_%20El.7elm.S01E36.HD/%5BCima-Now.CoM%5D%20El.7elm.S01E36.HD-480p.mp4",
      "size": "215.74 ميجا"
    },
    {
      "name": "Episode 37",
      "url": "https://deva-cpmav9sk6x20.cimanowtv.com/uploads/2022/02/21/_Cima-Now.CoM_%20El.7elm.S01E37.Final.HD/%5BCima-Now.CoM%5D%20El.7elm.S01E37.Final.HD-480p.mp4",
      "size": "236.17 ميجا"
    },
    {
      "name": "Episode 38",
      "url": "https://deva-cpmav9sk6x20.cimanowtv.com/uploads/2022/02/22/_Cima-Now.CoM_%20El.7elm.S01E38.Final.HD/%5BCima-Now.CoM%5D%20El.7elm.S01E38.Final.HD-480p.mp4",
      "size": "276.10 ميجا"
    }
  ]
}