{
  "title": "[EgyFilm] aygar 2dym S01",
  "episodes": [
    {
      "name": "Episode 01",
      "url": "https://deva-cpmav9sk6x25.cimanowtv.com/uploads/2022/10/28/_Cima-Now.CoM_%20Ejar.Adeem.S01E01.HD/%5BCima-Now.CoM%5D%20Ejar.Adeem.S01E01.HD-480p.mp4",
      "size": "262.30 ميجا"
    },
    {
      "name": "Episode 02",
      "url": "https://deva-cpmav9sk6x26.cimanowtv.com/uploads/2022/10/29/_Cima-Now.CoM_%20Ejar.Adeem.S01E02.HD/%5BCima-Now.CoM%5D%20Ejar.Adeem.S01E02.HD-480p.mp4",
      "size": "263.75 ميجا"
    },
    {
      "name": "Episode 03",
      "url": "https://deva-cpmav9sk6x25.cimanowtv.com/uploads/2022/10/30/_Cima-Now.CoM_%20Ejar.Adeem.S01E03.HD/%5BCima-Now.CoM%5D%20Ejar.Adeem.S01E03.HD-480p.mp4",
      "size": "233.44 ميجا"
    },
    {
      "name": "Episode 04",
      "url": "https://deva-cpmav9sk6x25.cimanowtv.com/uploads/2022/10/31/_Cima-Now.CoM_%20Ejar.Adeem.S01E04.HD/%5BCima-Now.CoM%5D%20Ejar.Adeem.S01E04.HD-480p.mp4",
      "size": "237.25 ميجا"
    },
    {
      "name": "Episode 05",
      "url": "https://deva-cpmav9sk6x25.cimanowtv.com/uploads/2022/11/01/_Cima-Now.CoM_%20Ejar.Adeem.S01E05.HD/%5BCima-Now.CoM%5D%20Ejar.Adeem.S01E05.HD-480p.mp4",
      "size": "219.43 ميجا"
    },
    {
      "name": "Episode 06",
      "url": "https://deva-cpmav9sk6x26.cimanowtv.com/uploads/2022/11/04/_Cima-Now.CoM_%20Ejar.Adeem.S01E06.HD/%5BCima-Now.CoM%5D%20Ejar.Adeem.S01E06.HD-480p.mp4",
      "size": "241.75 ميجا"
    },
    {
      "name": "Episode 07",
      "url": "https://deva-cpmav9sk6x26.cimanowtv.com/uploads/2022/11/05/_Cima-Now.CoM_%20Ejar.Adeem.S01E07.HD/%5BCima-Now.CoM%5D%20Ejar.Adeem.S01E07.HD-480p.mp4",
      "size": "206.08 ميجا"
    },
    {
      "name": "Episode 08",
      "url": "https://deva-cpmav9sk6x25.cimanowtv.com/uploads/2022/11/06/_Cima-Now.CoM_%20Ejar.Adeem.S01E08.HD/%5BCima-Now.CoM%5D%20Ejar.Adeem.S01E08.HD-480p.mp4",
      "size": "200.20 ميجا"
    },
    {
      "name": "Episode 09",
      "url": "https://deva-cpmav9sk6x25.cimanowtv.com/uploads/2022/11/07/_Cima-Now.CoM_%20Ejar.Adeem.S01E09.HD/%5BCima-Now.CoM%5D%20Ejar.Adeem.S01E09.HD-480p.mp4",
      "size": "207.76 ميجا"
    },
    {
      "name": "Episode 10",
      "url": "https://deva-cpmav9sk6x25.cimanowtv.com/uploads/2022/11/08/_Cima-Now.CoM_%20Ejar.Adeem.S01E10.HD/%5BCima-Now.CoM%5D%20Ejar.Adeem.S01E10.HD-480p.mp4",
      "size": "206.88 ميجا"
    },
    {
      "name": "Episode 11",
      "url": "https://deva-cpmav9sk6x25.cimanowtv.com/uploads/2022/11/11/_Cima-Now.CoM_%20Ejar.Adeem.S01E11.HD/%5BCima-Now.CoM%5D%20Ejar.Adeem.S01E11.HD-480p.mp4",
      "size": "202.28 ميجا"
    },
    {
      "name": "Episode 12",
      "url": "https://deva-cpmav9sk6x26.cimanowtv.com/uploads/2022/11/12/_Cima-Now.CoM_%20Ejar.Adeem.S01E12.HD/%5BCima-Now.CoM%5D%20Ejar.Adeem.S01E12.HD-480p.mp4",
      "size": "268.54 ميجا"
    },
    {
      "name": "Episode 13",
      "url": "https://deva-cpmav9sk6x26.cimanowtv.com/uploads/2022/11/13/_Cima-Now.CoM_%20Ejar.Adeem.S01E13.HD/%5BCima-Now.CoM%5D%20Ejar.Adeem.S01E13.HD-480p.mp4",
      "size": "206.22 ميجا"
    },
    {
      "name": "Episode 14",
      "url": "https://deva-cpmav9sk6x25.cimanowtv.com/uploads/2022/11/14/_Cima-Now.CoM_%20Ejar.Adeem.S01E14.HD/%5BCima-Now.CoM%5D%20Ejar.Adeem.S01E14.HD-480p.mp4",
      "size": "205.81 ميجا"
    },
    {
      "name": "Episode 15",
      "url": "https://deva-cpmav9sk6x26.cimanowtv.com/uploads/2022/11/15/_Cima-Now.CoM_%20Ejar.Adeem.S01E15.HD/%5BCima-Now.CoM%5D%20Ejar.Adeem.S01E15.HD-480p.mp4",
      "size": "213.40 ميجا"
    },
    {
      "name": "Episode 16",
      "url": "https://deva-cpmav9sk6x26.cimanowtv.com/uploads/2022/11/18/_Cima-Now.CoM_%20Ejar.Adeem.S01E16.HD/%5BCima-Now.CoM%5D%20Ejar.Adeem.S01E16.HD-480p.mp4",
      "size": "204.27 ميجا"
    },
    {
      "name": "Episode 17",
      "url": "https://deva-cpmav9sk6x25.cimanowtv.com/uploads/2022/11/19/_Cima-Now.CoM_%20Ejar.Adeem.S01E17.HD/%5BCima-Now.CoM%5D%20Ejar.Adeem.S01E17.HD-480p.mp4",
      "size": "204.54 ميجا"
    },
    {
      "name": "Episode 18",
      "url": "https://deva-cpmav9sk6x25.cimanowtv.com/uploads/2022/11/20/_Cima-Now.CoM_%20Ejar.Adeem.S01E18.HD/%5BCima-Now.CoM%5D%20Ejar.Adeem.S01E18.HD-480p.mp4",
      "size": "203.49 ميجا"
    },
    {
      "name": "Episode 19",
      "url": "https://deva-cpmav9sk6x25.cimanowtv.com/uploads/2022/11/21/_Cima-Now.CoM_%20Ejar.Adeem.S01E19.HD/%5BCima-Now.CoM%5D%20Ejar.Adeem.S01E19.HD-480p.mp4",
      "size": "205.01 ميجا"
    },
    {
      "name": "Episode 20",
      "url": "https://deva-cpmav9sk6x26.cimanowtv.com/uploads/2022/11/22/_Cima-Now.CoM_%20Ejar.Adeem.S01E20.HD/%5BCima-Now.CoM%5D%20Ejar.Adeem.S01E20.HD-480p.mp4",
      "size": "203.74 ميجا"
    },
    {
      "name": "Episode 21",
      "url": "https://deva-cpmav9sk6x25.cimanowtv.com/uploads/2022/11/25/_Cima-Now.CoM_%20Ejar.Adeem.S01E21.HD/%5BCima-Now.CoM%5D%20Ejar.Adeem.S01E21.HD-480p.mp4",
      "size": "196.34 ميجا"
    },
    {
      "name": "Episode 22",
      "url": "https://deva-cpmav9sk6x26.cimanowtv.com/uploads/2022/11/26/_Cima-Now.CoM_%20Ejar.Adeem.S01E22.HD/%5BCima-Now.CoM%5D%20Ejar.Adeem.S01E22.HD-480p.mp4",
      "size": "220.31 ميجا"
    },
    {
      "name": "Episode 23",
      "url": "https://deva-cpmav9sk6x26.cimanowtv.com/uploads/2022/11/27/_Cima-Now.CoM_%20Ejar.Adeem.S01E23.HD/%5BCima-Now.CoM%5D%20Ejar.Adeem.S01E23.HD-480p.mp4",
      "size": "240.37 ميجا"
    },
    {
      "name": "Episode 24",
      "url": "https://deva-cpmav9sk6x25.cimanowtv.com/uploads/2022/11/28/_Cima-Now.CoM_%20Ejar.Adeem.S01E24.HD/%5BCima-Now.CoM%5D%20Ejar.Adeem.S01E24.HD-480p.mp4",
      "size": "206.39 ميجا"
    },
    {
      "name": "Episode 25",
      "url": "https://deva-cpmav9sk6x26.cimanowtv.com/uploads/2022/11/29/_Cima-Now.CoM_%20Ejar.Adeem.S01E25.HD/%5BCima-Now.CoM%5D%20Ejar.Adeem.S01E25.HD-480p.mp4",
      "size": "201.19 ميجا"
    },
    {
      "name": "Episode 26",
      "url": "https://deva-cpmav9sk6x26.cimanowtv.com/uploads/2022/12/02/_Cima-Now.CoM_%20Ejar.Adeem.S01E26.HD/%5BCima-Now.CoM%5D%20Ejar.Adeem.S01E26.HD-480p.mp4",
      "size": "198.40 ميجا"
    },
    {
      "name": "Episode 27",
      "url": "https://deva-cpmav9sk6x26.cimanowtv.com/uploads/2022/12/03/_Cima-Now.CoM_%20Ejar.Adeem.S01E27.HD/%5BCima-Now.CoM%5D%20Ejar.Adeem.S01E27.HD-480p.mp4",
      "size": "205.38 ميجا"
    },
    {
      "name": "Episode 28",
      "url": "https://deva-cpmav9sk6x25.cimanowtv.com/uploads/2022/12/04/_Cima-Now.CoM_%20Ejar.Adeem.S01E28.HD/%5BCima-Now.CoM%5D%20Ejar.Adeem.S01E28.HD-480p.mp4",
      "size": "186.42 ميجا"
    },
    {
      "name": "Episode 29",
      "url": "https://deva-cpmav9sk6x25.cimanowtv.com/uploads/2022/12/05/_Cima-Now.CoM_%20Ejar.Adeem.S01E29.HD/%5BCima-Now.CoM%5D%20Ejar.Adeem.S01E29.HD-480p.mp4",
      "size": "198.23 ميجا"
    },
    {
      "name": "Episode 30",
      "url": "https://deva-cpmav9sk6x25.cimanowtv.com/uploads/2022/12/06/_Cima-Now.CoM_%20Ejar.Adeem.S01E30.HD/%5BCima-Now.CoM%5D%20Ejar.Adeem.S01E30.HD-480p.mp4",
      "size": "249.33 ميجا"
    }
  ]
}