{
  "title": "[EgyFilm] alnsyan S01",
  "episodes": [
    {
      "name": "Episode 01",
      "url": "https://deva-cpmav9sk6x33.cimanowtv.com/uploads/2024/05/18/_Cima-Now.CoM_%20El.Nisyan.S01E01.HD/%5BCima-Now.CoM%5D%20El.Nisyan.S01E01.HD-720p.mp4",
      "size": "512.83 ميجا"
    },
    {
      "name": "Episode 02",
      "url": "https://deva-cpmav9sk6x34.cimanowtv.com/uploads/2024/05/18/_Cima-Now.CoM_%20El.Nisyan.S01E02.HD/%5BCima-Now.CoM%5D%20El.Nisyan.S01E02.HD-720p.mp4",
      "size": "516.44 ميجا"
    },
    {
      "name": "Episode 03",
      "url": "https://deva-cpmav9sk6x34.cimanowtv.com/uploads/2024/05/18/_Cima-Now.CoM_%20El.Nisyan.S01E03.HD/%5BCima-Now.CoM%5D%20El.Nisyan.S01E03.HD-720p.mp4",
      "size": "412.42 ميجا"
    },
    {
      "name": "Episode 04",
      "url": "https://deva-cpmav9sk6x35.cimanowtv.com/uploads/2024/05/18/_Cima-Now.CoM_%20El.Nisyan.S01E04.HD/%5BCima-Now.CoM%5D%20El.Nisyan.S01E04.HD-720p.mp4",
      "size": "387.94 ميجا"
    },
    {
      "name": "Episode 05",
      "url": "https://deva-cpmav9sk6x35.cimanowtv.com/uploads/2024/05/18/_Cima-Now.CoM_%20El.Nisyan.S01E05.HD/%5BCima-Now.CoM%5D%20El.Nisyan.S01E05.HD-720p.mp4",
      "size": "418.34 ميجا"
    },
    {
      "name": "Episode 06",
      "url": "https://deva-cpmav9sk6x33.cimanowtv.com/uploads/2024/05/18/_Cima-Now.CoM_%20El.Nisyan.S01E06.HD/%5BCima-Now.CoM%5D%20El.Nisyan.S01E06.HD-720p.mp4",
      "size": "458.01 ميجا"
    },
    {
      "name": "Episode 07",
      "url": "https://deva-cpmav9sk6x34.cimanowtv.com/uploads/2024/05/18/_Cima-Now.CoM_%20El.Nisyan.S01E07.HD/%5BCima-Now.CoM%5D%20El.Nisyan.S01E07.HD-720p.mp4",
      "size": "473.70 ميجا"
    },
    {
      "name": "Episode 08",
      "url": "https://deva-cpmav9sk6x34.cimanowtv.com/uploads/2024/05/18/_Cima-Now.CoM_%20El.Nisyan.S01E08.HD/%5BCima-Now.CoM%5D%20El.Nisyan.S01E08.HD-720p.mp4",
      "size": "480.73 ميجا"
    },
    {
      "name": "Episode 09",
      "url": "https://deva-cpmav9sk6x35.cimanowtv.com/uploads/2024/05/18/_Cima-Now.CoM_%20El.Nisyan.S01E09.HD/%5BCima-Now.CoM%5D%20El.Nisyan.S01E09.HD-720p.mp4",
      "size": "453.07 ميجا"
    },
    {
      "name": "Episode 10",
      "url": "https://deva-cpmav9sk6x33.cimanowtv.com/uploads/2024/05/18/_Cima-Now.CoM_%20El.Nisyan.S01E10.HD/%5BCima-Now.CoM%5D%20El.Nisyan.S01E10.HD-720p.mp4",
      "size": "455.32 ميجا"
    },
    {
      "name": "Episode 11",
      "url": "https://deva-cpmav9sk6x34.cimanowtv.com/uploads/2024/05/18/_Cima-Now.CoM_%20El.Nisyan.S01E11.HD/%5BCima-Now.CoM%5D%20El.Nisyan.S01E11.HD-720p.mp4",
      "size": "406.12 ميجا"
    },
    {
      "name": "Episode 12",
      "url": "https://deva-cpmav9sk6x33.cimanowtv.com/uploads/2024/05/18/_Cima-Now.CoM_%20El.Nisyan.S01E12.HD/%5BCima-Now.CoM%5D%20El.Nisyan.S01E12.HD-720p.mp4",
      "size": "469.67 ميجا"
    },
    {
      "name": "Episode 13",
      "url": "https://deva-cpmav9sk6x34.cimanowtv.com/uploads/2024/05/18/_Cima-Now.CoM_%20El.Nisyan.S01E13.HD/%5BCima-Now.CoM%5D%20El.Nisyan.S01E13.HD-720p.mp4",
      "size": "447.27 ميجا"
    },
    {
      "name": "Episode 14",
      "url": "https://deva-cpmav9sk6x33.cimanowtv.com/uploads/2024/05/18/_Cima-Now.CoM_%20El.Nisyan.S01E14.HD/%5BCima-Now.CoM%5D%20El.Nisyan.S01E14.HD-720p.mp4",
      "size": "393.47 ميجا"
    },
    {
      "name": "Episode 15",
      "url": "https://deva-cpmav9sk6x34.cimanowtv.com/uploads/2024/05/18/_Cima-Now.CoM_%20El.Nisyan.S01E15.HD/%5BCima-Now.CoM%5D%20El.Nisyan.S01E15.HD-720p.mp4",
      "size": "458.96 ميجا"
    },
    {
      "name": "Episode 16",
      "url": "https://deva-cpmav9sk6x33.cimanowtv.com/uploads/2024/05/29/_Cima-Now.CoM_%20Waly.El.Aahd.S01E16.HD/%5BCima-Now.CoM%5D%20Waly.El.Aahd.S01E16.HD-720p.mp4",
      "size": "481.66 ميجا"
    },
    {
      "name": "Episode 17",
      "url": "https://deva-cpmav9sk6x34.cimanowtv.com/uploads/2024/05/30/_Cima-Now.CoM_%20Waly.El.Aahd.S01E17.HD/%5BCima-Now.CoM%5D%20Waly.El.Aahd.S01E17.HD-720p.mp4",
      "size": "451.83 ميجا"
    },
    {
      "name": "Episode 18",
      "url": "https://deva-cpmav9sk6x33.cimanowtv.com/uploads/2024/05/30/_Cima-Now.CoM_%20Waly.El.Aahd.S01E18.HD/%5BCima-Now.CoM%5D%20Waly.El.Aahd.S01E18.HD-720p.mp4",
      "size": "445.11 ميجا"
    },
    {
      "name": "Episode 19",
      "url": "https://deva-cpmav9sk6x34.cimanowtv.com/uploads/2024/05/31/_Cima-Now.CoM_%20Waly.El.Aahd.S01E19.HD/%5BCima-Now.CoM%5D%20Waly.El.Aahd.S01E19.HD-720p.mp4",
      "size": "444.13 ميجا"
    },
    {
      "name": "Episode 20",
      "url": "https://deva-cpmav9sk6x33.cimanowtv.com/uploads/2024/05/31/_Cima-Now.CoM_%20Waly.El.Aahd.S01E20.HD/%5BCima-Now.CoM%5D%20Waly.El.Aahd.S01E20.HD-720p.mp4",
      "size": "407.95 ميجا"
    },
    {
      "name": "Episode 21",
      "url": "https://deva-cpmav9sk6x34.cimanowtv.com/uploads/2024/06/01/_Cima-Now.CoM_%20Waly.El.Aahd.S01E21.HD/%5BCima-Now.CoM%5D%20Waly.El.Aahd.S01E21.HD-720p.mp4",
      "size": "405.69 ميجا"
    },
    {
      "name": "Episode 22",
      "url": "https://deva-cpmav9sk6x33.cimanowtv.com/uploads/2024/06/01/_Cima-Now.CoM_%20Waly.El.Aahd.S01E22.HD/%5BCima-Now.CoM%5D%20Waly.El.Aahd.S01E22.HD-720p.mp4",
      "size": "426.57 ميجا"
    },
    {
      "name": "Episode 23",
      "url": "https://deva-cpmav9sk6x34.cimanowtv.com/uploads/2024/06/02/_Cima-Now.CoM_%20Waly.El.Aahd.S01E23.HD/%5BCima-Now.CoM%5D%20Waly.El.Aahd.S01E23.HD-720p.mp4",
      "size": "405.91 ميجا"
    },
    {
      "name": "Episode 24",
      "url": "https://deva-cpmav9sk6x33.cimanowtv.com/uploads/2024/06/02/_Cima-Now.CoM_%20Waly.El.Aahd.S01E24.HD/%5BCima-Now.CoM%5D%20Waly.El.Aahd.S01E24.HD-720p.mp4",
      "size": "406.58 ميجا"
    },
    {
      "name": "Episode 25",
      "url": "https://deva-cpmav9sk6x34.cimanowtv.com/uploads/2024/06/03/_Cima-Now.CoM_%20Waly.El.Aahd.S01E25.HD/%5BCima-Now.CoM%5D%20Waly.El.Aahd.S01E25.HD-720p.mp4",
      "size": "392.16 ميجا"
    },
    {
      "name": "Episode 26",
      "url": "https://deva-cpmav9sk6x33.cimanowtv.com/uploads/2024/06/03/_Cima-Now.CoM_%20Waly.El.Aahd.S01E26.HD/%5BCima-Now.CoM%5D%20Waly.El.Aahd.S01E26.HD-720p.mp4",
      "size": "415.07 ميجا"
    },
    {
      "name": "Episode 27",
      "url": "https://deva-cpmav9sk6x34.cimanowtv.com/uploads/2024/06/04/_Cima-Now.CoM_%20Waly.El.Aahd.S01E27.HD/%5BCima-Now.CoM%5D%20Waly.El.Aahd.S01E27.HD-720p.mp4",
      "size": "442.60 ميجا"
    },
    {
      "name": "Episode 28",
      "url": "https://deva-cpmav9sk6x33.cimanowtv.com/uploads/2024/06/04/_Cima-Now.CoM_%20Waly.El.Aahd.S01E28.HD/%5BCima-Now.CoM%5D%20Waly.El.Aahd.S01E28.HD-720p.mp4",
      "size": "473.16 ميجا"
    },
    {
      "name": "Episode 29",
      "url": "https://deva-cpmav9sk6x34.cimanowtv.com/uploads/2024/06/05/_Cima-Now.CoM_%20Waly.El.Aahd.S01E29.HD/%5BCima-Now.CoM%5D%20Waly.El.Aahd.S01E29.HD-720p.mp4",
      "size": "445.06 ميجا"
    },
    {
      "name": "Episode 30",
      "url": "https://deva-cpmav9sk6x33.cimanowtv.com/uploads/2024/06/05/_Cima-Now.CoM_%20Waly.El.Aahd.S01E30.HD/%5BCima-Now.CoM%5D%20Waly.El.Aahd.S01E30.HD-720p.mp4",
      "size": "563.50 ميجا"
    }
  ]
}