{
  "title": "[EgyFilm] mwdw3 3a2ly S01",
  "episodes": [
    {
      "name": "Episode 01",
      "url": "https://deva-cpmav9sk6x18.cimanowtv.com/uploads/2021/11/24/_Cima-Now.CoM_%20Mawdo3.3alay.S01E01.HD/%5BCima-Now.CoM%5D%20Mawdo3.3alay.S01E01.HD-720p.mp4",
      "size": "519.74 ميجا"
    },
    {
      "name": "Episode 02",
      "url": "https://deva-cpmav9sk6x16.cimanowtv.com/uploads/2021/11/25/_Cima-Now.CoM_%20Mawdo3.3alay.S01E02.HD/%5BCima-Now.CoM%5D%20Mawdo3.3alay.S01E02.HD-720p.mp4",
      "size": "424.25 ميجا"
    },
    {
      "name": "Episode 03",
      "url": "https://deva-cpmav9sk6x18.cimanowtv.com/uploads/2021/11/27/_Cima-Now.CoM_%20Mawdo3.3alay.S01E03.HD/%5BCima-Now.CoM%5D%20Mawdo3.3alay.S01E03.HD-720p.mp4",
      "size": "508.06 ميجا"
    },
    {
      "name": "Episode 04",
      "url": "https://deva-cpmav9sk6x16.cimanowtv.com/uploads/2021/12/01/_Cima-Now.CoM_%20Mawdo3.3alay.S01E04.HD/%5BCima-Now.CoM%5D%20Mawdo3.3alay.S01E04.HD-720p.mp4",
      "size": "476.26 ميجا"
    },
    {
      "name": "Episode 05",
      "url": "https://deva-cpmav9sk6x17.cimanowtv.com/uploads/2021/12/02/_Cima-Now.CoM_%20Mawdo3.3alay.S01E05.HD/%5BCima-Now.CoM%5D%20Mawdo3.3alay.S01E05.HD-720p.mp4",
      "size": "417.44 ميجا"
    },
    {
      "name": "Episode 06",
      "url": "https://deva-cpmav9sk6x16.cimanowtv.com/uploads/2021/12/04/_Cima-Now.CoM_%20Mawdo3.3alay.S01E06.HD/%5BCima-Now.CoM%5D%20Mawdo3.3alay.S01E06.HD-720p.mp4",
      "size": "414.58 ميجا"
    },
    {
      "name": "Episode 07",
      "url": "https://deva-cpmav9sk6x16.cimanowtv.com/uploads/2021/12/09/_Cima-Now.CoM_%20Mawdo3.3alay.S01E07.HD/%5BCima-Now.CoM%5D%20Mawdo3.3alay.S01E07.HD-720p.mp4",
      "size": "540.11 ميجا"
    },
    {
      "name": "Episode 08",
      "url": "https://deva-cpmav9sk6x17.cimanowtv.com/uploads/2021/12/10/_Cima-Now.CoM_%20Mawdo3.3alay.S01E08.HD/%5BCima-Now.CoM%5D%20Mawdo3.3alay.S01E08.HD-720p.mp4",
      "size": "475.02 ميجا"
    },
    {
      "name": "Episode 09",
      "url": "https://deva-cpmav9sk6x18.cimanowtv.com/uploads/2021/12/16/_Cima-Now.CoM_%20Mawdo3.3alay.S01E09.HD/%5BCima-Now.CoM%5D%20Mawdo3.3alay.S01E09.HD-720p.mp4",
      "size": "352.68 ميجا"
    },
    {
      "name": "Episode 10",
      "url": "https://deva-cpmav9sk6x18.cimanowtv.com/uploads/2021/12/17/_Cima-Now.CoM_%20Mawdo3.3alay.S01E10.HD/%5BCima-Now.CoM%5D%20Mawdo3.3alay.S01E10.HD-720p.mp4",
      "size": "644.53 ميجا"
    },
    {
      "name": "Episode 11",
      "url": "https://deva-cpmav9sk6x18.cimanowtv.com/uploads/2021/12/12/_Cima-Now.CoM_%20Shati.Ya.Beirut.S01E11.HD/%5BCima-Now.CoM%5D%20Shati.Ya.Beirut.S01E11.HD-720p.mp4",
      "size": "334.48 ميجا"
    },
    {
      "name": "Episode 12",
      "url": "https://deva-cpmav9sk6x17.cimanowtv.com/uploads/2021/12/12/_Cima-Now.CoM_%20Shati.Ya.Beirut.S01E12.HD/%5BCima-Now.CoM%5D%20Shati.Ya.Beirut.S01E12.HD-720p.mp4",
      "size": "326.43 ميجا"
    },
    {
      "name": "Episode 13",
      "url": "https://deva-cpmav9sk6x18.cimanowtv.com/uploads/2021/12/14/_Cima-Now.CoM_%20Shati.Ya.Beirut.S01E13.HD/%5BCima-Now.CoM%5D%20Shati.Ya.Beirut.S01E13.HD-720p.mp4",
      "size": "329.09 ميجا"
    },
    {
      "name": "Episode 14",
      "url": "https://deva-cpmav9sk6x18.cimanowtv.com/uploads/2021/12/15/_Cima-Now.CoM_%20Shati.Ya.Beirut.S01E14.HD/%5BCima-Now.CoM%5D%20Shati.Ya.Beirut.S01E14.HD-720p.mp4",
      "size": "342.36 ميجا"
    },
    {
      "name": "Episode 15",
      "url": "https://deva-cpmav9sk6x16.cimanowtv.com/uploads/2021/12/16/_Cima-Now.CoM_%20Shati.Ya.Beirut.S01E15.HD/%5BCima-Now.CoM%5D%20Shati.Ya.Beirut.S01E15.HD-720p.mp4",
      "size": "348.54 ميجا"
    },
    {
      "name": "Episode 16",
      "url": "https://deva-cpmav9sk6x17.cimanowtv.com/uploads/2021/12/18/_Cima-Now.CoM_%20Shati.Ya.Beirut.S01E16.HD/%5BCima-Now.CoM%5D%20Shati.Ya.Beirut.S01E16.HD-720p.mp4",
      "size": "356.73 ميجا"
    },
    {
      "name": "Episode 17",
      "url": "https://deva-cpmav9sk6x18.cimanowtv.com/uploads/2021/12/19/_Cima-Now.CoM_%20Shati.Ya.Beirut.S01E17.HD/%5BCima-Now.CoM%5D%20Shati.Ya.Beirut.S01E17.HD-720p.mp4",
      "size": "348.37 ميجا"
    },
    {
      "name": "Episode 18",
      "url": "https://deva-cpmav9sk6x16.cimanowtv.com/uploads/2021/12/21/_Cima-Now.CoM_%20Shati.Ya.Beirut.S01E18.HD/%5BCima-Now.CoM%5D%20Shati.Ya.Beirut.S01E18.HD-720p.mp4",
      "size": "336.37 ميجا"
    },
    {
      "name": "Episode 19",
      "url": "https://deva-cpmav9sk6x17.cimanowtv.com/uploads/2021/12/22/_Cima-Now.CoM_%20Shati.Ya.Beirut.S01E19.HD/%5BCima-Now.CoM%5D%20Shati.Ya.Beirut.S01E19.HD-720p.mp4",
      "size": "355.84 ميجا"
    },
    {
      "name": "Episode 20",
      "url": "https://deva-cpmav9sk6x17.cimanowtv.com/uploads/2021/12/23/_Cima-Now.CoM_%20Shati.Ya.Beirut.S01E20.HD/%5BCima-Now.CoM%5D%20Shati.Ya.Beirut.S01E20.HD-720p.mp4",
      "size": "315.76 ميجا"
    },
    {
      "name": "Episode 21",
      "url": "https://deva-cpmav9sk6x17.cimanowtv.com/uploads/2021/12/25/_Cima-Now.CoM_%20Shati.Ya.Beirut.S01E21.HD/%5BCima-Now.CoM%5D%20Shati.Ya.Beirut.S01E21.HD-720p.mp4",
      "size": "327.35 ميجا"
    },
    {
      "name": "Episode 22",
      "url": "https://deva-cpmav9sk6x18.cimanowtv.com/uploads/2021/12/26/_Cima-Now.CoM_%20Shati.Ya.Beirut.S01E22.HD/%5BCima-Now.CoM%5D%20Shati.Ya.Beirut.S01E22.HD-720p.mp4",
      "size": "330.31 ميجا"
    },
    {
      "name": "Episode 23",
      "url": "https://deva-cpmav9sk6x16.cimanowtv.com/uploads/2021/12/28/_Cima-Now.CoM_%20Shati.Ya.Beirut.S01E23.HD/%5BCima-Now.CoM%5D%20Shati.Ya.Beirut.S01E23.HD-720p.mp4",
      "size": "341.80 ميجا"
    },
    {
      "name": "Episode 24",
      "url": "https://deva-cpmav9sk6x16.cimanowtv.com/uploads/2021/12/29/_Cima-Now.CoM_%20Shati.Ya.Beirut.S01E24.HD/%5BCima-Now.CoM%5D%20Shati.Ya.Beirut.S01E24.HD-720p.mp4",
      "size": "320.57 ميجا"
    },
    {
      "name": "Episode 25",
      "url": "https://deva-cpmav9sk6x17.cimanowtv.com/uploads/2021/12/30/_Cima-Now.CoM_%20Shati.Ya.Beirut.S01E25.HD/%5BCima-Now.CoM%5D%20Shati.Ya.Beirut.S01E25.HD-720p.mp4",
      "size": "354.60 ميجا"
    },
    {
      "name": "Episode 26",
      "url": "https://deva-cpmav9sk6x19.cimanowtv.com/uploads/2022/01/03/_Cima-Now.CoM_%20Shati.Ya.Beirut.S01E26.HD/%5BCima-Now.CoM%5D%20Shati.Ya.Beirut.S01E26.HD-720p.mp4",
      "size": "320.82 ميجا"
    },
    {
      "name": "Episode 27",
      "url": "https://deva-cpmav9sk6x19.cimanowtv.com/uploads/2022/01/03/_Cima-Now.CoM_%20Shati.Ya.Beirut.S01E27.HD/%5BCima-Now.CoM%5D%20Shati.Ya.Beirut.S01E27.HD-720p.mp4",
      "size": "323.52 ميجا"
    },
    {
      "name": "Episode 28",
      "url": "https://deva-cpmav9sk6x20.cimanowtv.com/uploads/2022/01/03/_Cima-Now.CoM_%20Shati.Ya.Beirut.S01E28.HD/%5BCima-Now.CoM%5D%20Shati.Ya.Beirut.S01E28.HD-720p.mp4",
      "size": "334.96 ميجا"
    },
    {
      "name": "Episode 29",
      "url": "https://deva-cpmav9sk6x20.cimanowtv.com/uploads/2022/01/04/_Cima-Now.CoM_%20Shati.Ya.Beirut.S01E29.HD/%5BCima-Now.CoM%5D%20Shati.Ya.Beirut.S01E29.HD-720p.mp4",
      "size": "321.82 ميجا"
    },
    {
      "name": "Episode 30",
      "url": "https://deva-cpmav9sk6x21.cimanowtv.com/uploads/2022/01/05/_Cima-Now.CoM_%20Shati.Ya.Beirut.S01E30.HD/%5BCima-Now.CoM%5D%20Shati.Ya.Beirut.S01E30.HD-720p.mp4",
      "size": "398.92 ميجا"
    },
    {
      "name": "Episode 31",
      "url": "https://deva-cpmav9sk6x21.cimanowtv.com/uploads/2022/01/08/_Cima-Now.CoM_%20Naseby.WE.Qsmtk.S04E31.HD/%5BCima-Now.CoM%5D%20Naseby.WE.Qsmtk.S04E31.HD-720p.mp4",
      "size": "412.29 ميجا"
    },
    {
      "name": "Episode 32",
      "url": "https://deva-cpmav9sk6x20.cimanowtv.com/uploads/2022/01/09/_Cima-Now.CoM_%20Naseby.WE.Qsmtk.S04E32.HD/%5BCima-Now.CoM%5D%20Naseby.WE.Qsmtk.S04E32.HD-720p.mp4",
      "size": "331.91 ميجا"
    },
    {
      "name": "Episode 33",
      "url": "https://deva-cpmav9sk6x21.cimanowtv.com/uploads/2022/01/10/_Cima-Now.CoM_%20Naseby.WE.Qsmtk.S04E33.HD/%5BCima-Now.CoM%5D%20Naseby.WE.Qsmtk.S04E33.HD-720p.mp4",
      "size": "395.37 ميجا"
    },
    {
      "name": "Episode 34",
      "url": "https://deva-cpmav9sk6x20.cimanowtv.com/uploads/2022/01/11/_Cima-Now.CoM_%20Naseby.WE.Qsmtk.S04E34.HD/%5BCima-Now.CoM%5D%20Naseby.WE.Qsmtk.S04E34.HD-720p.mp4",
      "size": "347.26 ميجا"
    },
    {
      "name": "Episode 35",
      "url": "https://deva-cpmav9sk6x21.cimanowtv.com/uploads/2022/01/12/_Cima-Now.CoM_%20Naseby.WE.Qsmtk.S04E35.HD/%5BCima-Now.CoM%5D%20Naseby.WE.Qsmtk.S04E35.HD-720p.mp4",
      "size": "486.20 ميجا"
    },
    {
      "name": "Episode 36",
      "url": "https://deva-cpmav9sk6x19.cimanowtv.com/uploads/2022/01/15/_Cima-Now.CoM_%20Naseby.WE.Qsmtk.S04E36.HD/%5BCima-Now.CoM%5D%20Naseby.WE.Qsmtk.S04E36.HD-720p.mp4",
      "size": "506.90 ميجا"
    },
    {
      "name": "Episode 37",
      "url": "https://deva-cpmav9sk6x20.cimanowtv.com/uploads/2022/01/16/_Cima-Now.CoM_%20Naseby.WE.Qsmtk.S04E37.HD/%5BCima-Now.CoM%5D%20Naseby.WE.Qsmtk.S04E37.HD-720p.mp4",
      "size": "402.02 ميجا"
    },
    {
      "name": "Episode 38",
      "url": "https://deva-cpmav9sk6x21.cimanowtv.com/uploads/2022/01/17/_Cima-Now.CoM_%20Naseby.WE.Qsmtk.S04E38.HD/%5BCima-Now.CoM%5D%20Naseby.WE.Qsmtk.S04E38.HD-720p.mp4",
      "size": "471.26 ميجا"
    },
    {
      "name": "Episode 39",
      "url": "https://deva-cpmav9sk6x19.cimanowtv.com/uploads/2022/01/18/_Cima-Now.CoM_%20Naseby.WE.Qsmtk.S04E39.HD/%5BCima-Now.CoM%5D%20Naseby.WE.Qsmtk.S04E39.HD-720p.mp4",
      "size": "406.75 ميجا"
    },
    {
      "name": "Episode 40",
      "url": "https://deva-cpmav9sk6x20.cimanowtv.com/uploads/2022/01/19/_Cima-Now.CoM_%20Naseby.WE.Qsmtk.S04E40.HD/%5BCima-Now.CoM%5D%20Naseby.WE.Qsmtk.S04E40.HD-720p.mp4",
      "size": "416.52 ميجا"
    }
  ]
}