{
  "title": "[EgyFilm] btn al7wt S01",
  "episodes": [
    {
      "name": "Episode 01",
      "url": "https://deva-cpmav9sk6x31.cimanowtv.com/uploads/2023/11/23/_Cima-Now.CoM_%20Batn.El.7oot.S01E01.HD/%5BCima-Now.CoM%5D%20Batn.El.7oot.S01E01.HD-480p.mp4",
      "size": "262.77 ميجا"
    },
    {
      "name": "Episode 02",
      "url": "https://deva-cpmav9sk6x32.cimanowtv.com/uploads/2023/11/23/_Cima-Now.CoM_%20Batn.El.7oot.S01E02.HD/%5BCima-Now.CoM%5D%20Batn.El.7oot.S01E02.HD-480p.mp4",
      "size": "229.56 ميجا"
    },
    {
      "name": "Episode 03",
      "url": "https://deva-cpmav9sk6x32.cimanowtv.com/uploads/2023/11/23/_Cima-Now.CoM_%20Batn.El.7oot.S01E03.HD/%5BCima-Now.CoM%5D%20Batn.El.7oot.S01E03.HD-480p.mp4",
      "size": "245.13 ميجا"
    },
    {
      "name": "Episode 04",
      "url": "https://deva-cpmav9sk6x30.cimanowtv.com/uploads/2023/11/30/_Cima-Now.CoM_%20Batn.El.7oot.S01E04.HD/%5BCima-Now.CoM%5D%20Batn.El.7oot.S01E04.HD-480p.mp4",
      "size": "229.53 ميجا"
    },
    {
      "name": "Episode 05",
      "url": "https://deva-cpmav9sk6x32.cimanowtv.com/uploads/2023/11/30/_Cima-Now.CoM_%20Batn.El.7oot.S01E05.HD/%5BCima-Now.CoM%5D%20Batn.El.7oot.S01E05.HD-480p.mp4",
      "size": "292.28 ميجا"
    },
    {
      "name": "Episode 06",
      "url": "https://deva-cpmav9sk6x32.cimanowtv.com/uploads/2023/12/07/_Cima-Now.CoM_%20Batn.El.7oot.S01E06.HD/%5BCima-Now.CoM%5D%20Batn.El.7oot.S01E06.HD-480p.mp4",
      "size": "247.99 ميجا"
    },
    {
      "name": "Episode 07",
      "url": "https://deva-cpmav9sk6x30.cimanowtv.com/uploads/2023/12/07/_Cima-Now.CoM_%20Batn.El.7oot.S01E07.HD/%5BCima-Now.CoM%5D%20Batn.El.7oot.S01E07.HD-480p.mp4",
      "size": "276.51 ميجا"
    },
    {
      "name": "Episode 08",
      "url": "https://deva-cpmav9sk6x30.cimanowtv.com/uploads/2023/12/14/_Cima-Now.CoM_%20Batn.El.7oot.S01E08.HD/%5BCima-Now.CoM%5D%20Batn.El.7oot.S01E08.HD-480p.mp4",
      "size": "237.84 ميجا"
    },
    {
      "name": "Episode 09",
      "url": "https://deva-cpmav9sk6x32.cimanowtv.com/uploads/2023/12/14/_Cima-Now.CoM_%20Batn.El.7oot.S01E09.HD/%5BCima-Now.CoM%5D%20Batn.El.7oot.S01E09.HD-480p.mp4",
      "size": "239.40 ميجا"
    },
    {
      "name": "Episode 10",
      "url": "https://deva-cpmav9sk6x32.cimanowtv.com/uploads/2023/12/21/_Cima-Now.CoM_%20Batn.El.7oot.S01E10.HD/%5BCima-Now.CoM%5D%20Batn.El.7oot.S01E10.HD-480p.mp4",
      "size": "227.46 ميجا"
    },
    {
      "name": "Episode 11",
      "url": "https://deva-cpmav9sk6x31.cimanowtv.com/uploads/2023/12/21/_Cima-Now.CoM_%20Batn.El.7oot.S01E11.HD/%5BCima-Now.CoM%5D%20Batn.El.7oot.S01E11.HD-480p.mp4",
      "size": "201.00 ميجا"
    },
    {
      "name": "Episode 12",
      "url": "https://deva-cpmav9sk6x31.cimanowtv.com/uploads/2023/12/28/_Cima-Now.CoM_%20Batn.El.7oot.S01E12.HD/%5BCima-Now.CoM%5D%20Batn.El.7oot.S01E12.HD-480p.mp4",
      "size": "249.97 ميجا"
    },
    {
      "name": "Episode 13",
      "url": "https://deva-cpmav9sk6x32.cimanowtv.com/uploads/2023/12/28/_Cima-Now.CoM_%20Batn.El.7oot.S01E13.HD/%5BCima-Now.CoM%5D%20Batn.El.7oot.S01E13.HD-480p.mp4",
      "size": "247.51 ميجا"
    },
    {
      "name": "Episode 14",
      "url": "https://deva-cpmav9sk6x30.cimanowtv.com/uploads/2024/01/04/_Cima-Now.CoM_%20Batn.El.7oot.S01E14.HD/%5BCima-Now.CoM%5D%20Batn.El.7oot.S01E14.HD-480p.mp4",
      "size": "244.34 ميجا"
    },
    {
      "name": "Episode 15",
      "url": "https://deva-cpmav9sk6x32.cimanowtv.com/uploads/2024/01/04/_Cima-Now.CoM_%20Batn.El.7oot.S01E15.HD/%5BCima-Now.CoM%5D%20Batn.El.7oot.S01E15.HD-480p.mp4",
      "size": "247.91 ميجا"
    }
  ]
}