{
  "title": "[EgyFilm] alshrn2a S01",
  "episodes": [
    {
      "name": "Episode 01",
      "url": "https://deva-cpmav9sk6x38.cimanowtv.com/uploads/2025/02/27/_Cima-Now.CoM_%20El.Sharnaqa.S01E01.HD/%5BCima-Now.CoM%5D%20El.Sharnaqa.S01E01.HD-720p.mp4",
      "size": "482.36 ميجا"
    },
    {
      "name": "Episode 02",
      "url": "https://deva-cpmav9sk6x37.cimanowtv.com/uploads/2025/02/28/_Cima-Now.CoM_%20El.Sharnaqa.S01E02.HD/%5BCima-Now.CoM%5D%20El.Sharnaqa.S01E02.HD-720p.mp4",
      "size": "415.25 ميجا"
    },
    {
      "name": "Episode 03",
      "url": "https://deva-cpmav9sk6x37.cimanowtv.com/uploads/2025/03/01/_Cima-Now.CoM_%20El.Sharnaqa.S01E03.HD/%5BCima-Now.CoM%5D%20El.Sharnaqa.S01E03.HD-720p.mp4",
      "size": "418.73 ميجا"
    },
    {
      "name": "Episode 04",
      "url": "https://deva-cpmav9sk6x36.cimanowtv.com/uploads/2025/03/02/_Cima-Now.CoM_%20El.Sharnaqa.S01E04.HD/%5BCima-Now.CoM%5D%20El.Sharnaqa.S01E04.HD-720p.mp4",
      "size": "349.18 ميجا"
    },
    {
      "name": "Episode 05",
      "url": "https://deva-cpmav9sk6x37.cimanowtv.com/uploads/2025/03/03/_Cima-Now.CoM_%20El.Sharnaqa.S01E05.HD/%5BCima-Now.CoM%5D%20El.Sharnaqa.S01E05.HD-720p.mp4",
      "size": "352.33 ميجا"
    },
    {
      "name": "Episode 06",
      "url": "https://deva-cpmav9sk6x38.cimanowtv.com/uploads/2025/03/04/_Cima-Now.CoM_%20El.Sharnaqa.S01E06.HD/%5BCima-Now.CoM%5D%20El.Sharnaqa.S01E06.HD-720p.mp4",
      "size": "382.00 ميجا"
    },
    {
      "name": "Episode 07",
      "url": "https://deva-cpmav9sk6x38.cimanowtv.com/uploads/2025/03/05/_Cima-Now.CoM_%20El.Sharnaqa.S01E07.HD/%5BCima-Now.CoM%5D%20El.Sharnaqa.S01E07.HD-720p.mp4",
      "size": "289.99 ميجا"
    },
    {
      "name": "Episode 08",
      "url": "https://deva-cpmav9sk6x36.cimanowtv.com/uploads/2025/03/06/_Cima-Now.CoM_%20El.Sharnaqa.S01E08.HD/%5BCima-Now.CoM%5D%20El.Sharnaqa.S01E08.HD-720p.mp4",
      "size": "325.27 ميجا"
    },
    {
      "name": "Episode 09",
      "url": "https://deva-cpmav9sk6x36.cimanowtv.com/uploads/2025/03/07/_Cima-Now.CoM_%20El.Sharnaqa.S01E09.HD/%5BCima-Now.CoM%5D%20El.Sharnaqa.S01E09.HD-720p.mp4",
      "size": "364.86 ميجا"
    },
    {
      "name": "Episode 10",
      "url": "https://deva-cpmav9sk6x37.cimanowtv.com/uploads/2025/03/08/_Cima-Now.CoM_%20El.Sharnaqa.S01E10.HD/%5BCima-Now.CoM%5D%20El.Sharnaqa.S01E10.HD-720p.mp4",
      "size": "292.14 ميجا"
    },
    {
      "name": "Episode 11",
      "url": "https://deva-cpmav9sk6x38.cimanowtv.com/uploads/2025/03/09/_Cima-Now.CoM_%20El.Sharnaqa.S01E11.HD/%5BCima-Now.CoM%5D%20El.Sharnaqa.S01E11.HD-720p.mp4",
      "size": "388.34 ميجا"
    },
    {
      "name": "Episode 12",
      "url": "https://deva-cpmav9sk6x36.cimanowtv.com/uploads/2025/03/10/_Cima-Now.CoM_%20El.Sharnaqa.S01E12.HD/%5BCima-Now.CoM%5D%20El.Sharnaqa.S01E12.HD-720p.mp4",
      "size": "351.75 ميجا"
    },
    {
      "name": "Episode 13",
      "url": "https://deva-cpmav9sk6x38.cimanowtv.com/uploads/2025/03/11/_Cima-Now.CoM_%20El.Sharnaqa.S01E13.HD/%5BCima-Now.CoM%5D%20El.Sharnaqa.S01E13.HD-720p.mp4",
      "size": "285.26 ميجا"
    },
    {
      "name": "Episode 15",
      "url": "https://deva-cpmav9sk6x37.cimanowtv.com/uploads/2025/03/13/_Cima-Now.CoM_%20El.Sharnaqa.S01E15.HD/%5BCima-Now.CoM%5D%20El.Sharnaqa.S01E15.HD-720p.mp4",
      "size": "418.86 ميجا"
    }
  ]
}