{
  "title": "[EgyFilm] 2ar2a alfngan S01",
  "episodes": [
    {
      "name": "Episode 01",
      "url": "https://deva-cpmav9sk6x11.cimanowtv.com/uploads/2021/03/12/_Cima-Now.CoM_%20Qariat.El.Fingan.S01E01.HD/%5BCima-Now.CoM%5D%20Qariat.El.Fingan.S01E01.HD-1080p.mp4",
      "size": "736.55 ميجا"
    },
    {
      "name": "Episode 02",
      "url": "https://deva-cpmav9sk6x10.cimanowtv.com/uploads/2021/03/11/_Cima-Now.CoM_%20Qariat.El.Fingan.S01E02.HD/%5BCima-Now.CoM%5D%20Qariat.El.Fingan.S01E02.HD-1080p.mp4",
      "size": "614.02 ميجا"
    },
    {
      "name": "Episode 03",
      "url": "https://deva-cpmav9sk6x9.cimanowtv.com/uploads/2021/03/18/_Cima-Now.CoM_%20Qariat.El.Fingan.S01E03.HD/%5BCima-Now.CoM%5D%20Qariat.El.Fingan.S01E03.HD-1080p.mp4",
      "size": "648.57 ميجا"
    },
    {
      "name": "Episode 04",
      "url": "https://deva-cpmav9sk6x9.cimanowtv.com/uploads/2021/03/18/_Cima-Now.CoM_%20Qariat.El.Fingan.S01E04.HD/%5BCima-Now.CoM%5D%20Qariat.El.Fingan.S01E04.HD-1080p.mp4",
      "size": "577.54 ميجا"
    },
    {
      "name": "Episode 05",
      "url": "https://deva-cpmav9sk6x11.cimanowtv.com/uploads/2021/03/25/_Cima-Now.CoM_%20Qariat.El.Fingan.S01E05.HD/%5BCima-Now.CoM%5D%20Qariat.El.Fingan.S01E05.HD-1080p.mp4",
      "size": "679.53 ميجا"
    },
    {
      "name": "Episode 06",
      "url": "https://deva-cpmav9sk6x11.cimanowtv.com/uploads/2021/03/26/_Cima-Now.CoM_%20Qariat.El.Fingan.S01E06.HD/%5BCima-Now.CoM%5D%20Qariat.El.Fingan.S01E06.HD-1080p.mp4",
      "size": "563.38 ميجا"
    },
    {
      "name": "Episode 07",
      "url": "https://deva-cpmav9sk6x11.cimanowtv.com/uploads/2021/04/02/_Cima-Now.CoM_%20Qariat.El.Fingan.S01E07.HD/%5BCima-Now.CoM%5D%20Qariat.El.Fingan.S01E07.HD-1080p.mp4",
      "size": "716.55 ميجا"
    },
    {
      "name": "Episode 08",
      "url": "https://deva-cpmav9sk6x10.cimanowtv.com/uploads/2021/04/02/_Cima-Now.CoM_%20Qariat.El.Fingan.S01E08.HD/%5BCima-Now.CoM%5D%20Qariat.El.Fingan.S01E08.HD-1080p.mp4",
      "size": "643.47 ميجا"
    },
    {
      "name": "Episode 09",
      "url": "https://deva-cpmav9sk6x10.cimanowtv.com/uploads/2021/04/08/_Cima-Now.CoM_%20Qariat.El.Fingan.S01E09.HD/%5BCima-Now.CoM%5D%20Qariat.El.Fingan.S01E09.HD-1080p.mp4",
      "size": "643.53 ميجا"
    },
    {
      "name": "Episode 10",
      "url": "https://deva-cpmav9sk6x10.cimanowtv.com/uploads/2021/04/08/_Cima-Now.CoM_%20Qariat.El.Fingan.S01E10.HD/%5BCima-Now.CoM%5D%20Qariat.El.Fingan.S01E10.HD-1080p.mp4",
      "size": "575.96 ميجا"
    }
  ]
}