{
  "title": "[EgyFilm] khald nwr wwldh nwr khald S01",
  "episodes": [
    {
      "name": "Episode 01",
      "url": "https://deva-cpmav9sk6x30.cimanowtv.com/uploads/2024/03/25/_Cima-Now.CoM_%20Khaled.Nour.And.His.Son.S01E01.HD/%5BCima-Now.CoM%5D%20Khaled.Nour.And.His.Son.S01E01.HD-480p.mp4",
      "size": "283.34 ميجا"
    },
    {
      "name": "Episode 02",
      "url": "https://deva-cpmav9sk6x32.cimanowtv.com/uploads/2024/03/25/_Cima-Now.CoM_%20Khaled.Nour.And.His.Son.S01E02.HD/%5BCima-Now.CoM%5D%20Khaled.Nour.And.His.Son.S01E02.HD-480p.mp4",
      "size": "292.52 ميجا"
    },
    {
      "name": "Episode 03",
      "url": "https://deva-cpmav9sk6x30.cimanowtv.com/uploads/2024/03/26/_Cima-Now.CoM_%20Khaled.Nour.And.His.Son.S01E03.HD/%5BCima-Now.CoM%5D%20Khaled.Nour.And.His.Son.S01E03.HD-480p.mp4",
      "size": "246.03 ميجا"
    },
    {
      "name": "Episode 04",
      "url": "https://deva-cpmav9sk6x32.cimanowtv.com/uploads/2024/03/27/_Cima-Now.CoM_%20Khaled.Nour.And.His.Son.S01E04.HD/%5BCima-Now.CoM%5D%20Khaled.Nour.And.His.Son.S01E04.HD-480p.mp4",
      "size": "277.62 ميجا"
    },
    {
      "name": "Episode 05",
      "url": "https://deva-cpmav9sk6x32.cimanowtv.com/uploads/2024/03/28/_Cima-Now.CoM_%20Khaled.Nour.And.His.Son.S01E05.HD/%5BCima-Now.CoM%5D%20Khaled.Nour.And.His.Son.S01E05.HD-480p.mp4",
      "size": "251.43 ميجا"
    },
    {
      "name": "Episode 06",
      "url": "https://deva-cpmav9sk6x32.cimanowtv.com/uploads/2024/03/29/_Cima-Now.CoM_%20Khaled.Nour.And.His.Son.S01E06.HD/%5BCima-Now.CoM%5D%20Khaled.Nour.And.His.Son.S01E06.HD-480p.mp4",
      "size": "267.12 ميجا"
    },
    {
      "name": "Episode 07",
      "url": "https://deva-cpmav9sk6x31.cimanowtv.com/uploads/2024/03/30/_Cima-Now.CoM_%20Khaled.Nour.And.His.Son.S01E07.HD/%5BCima-Now.CoM%5D%20Khaled.Nour.And.His.Son.S01E07.HD-480p.mp4",
      "size": "261.36 ميجا"
    },
    {
      "name": "Episode 08",
      "url": "https://deva-cpmav9sk6x31.cimanowtv.com/uploads/2024/03/31/_Cima-Now.CoM_%20Khaled.Nour.And.His.Son.S01E08.HD/%5BCima-Now.CoM%5D%20Khaled.Nour.And.His.Son.S01E08.HD-480p.mp4",
      "size": "257.96 ميجا"
    },
    {
      "name": "Episode 09",
      "url": "https://deva-cpmav9sk6x31.cimanowtv.com/uploads/2024/04/01/_Cima-Now.CoM_%20Khaled.Nour.And.His.Son.S01E09.HD/%5BCima-Now.CoM%5D%20Khaled.Nour.And.His.Son.S01E09.HD-480p.mp4",
      "size": "251.70 ميجا"
    },
    {
      "name": "Episode 10",
      "url": "https://deva-cpmav9sk6x31.cimanowtv.com/uploads/2024/04/02/_Cima-Now.CoM_%20Khaled.Nour.And.His.Son.S01E10.HD/%5BCima-Now.CoM%5D%20Khaled.Nour.And.His.Son.S01E10.HD-480p.mp4",
      "size": "242.17 ميجا"
    },
    {
      "name": "Episode 11",
      "url": "https://deva-cpmav9sk6x30.cimanowtv.com/uploads/2024/04/03/_Cima-Now.CoM_%20Khaled.Nour.And.His.Son.S01E11.HD/%5BCima-Now.CoM%5D%20Khaled.Nour.And.His.Son.S01E11.HD-480p.mp4",
      "size": "230.66 ميجا"
    },
    {
      "name": "Episode 12",
      "url": "https://deva-cpmav9sk6x30.cimanowtv.com/uploads/2024/04/04/_Cima-Now.CoM_%20Khaled.Nour.And.His.Son.S01E12.HD/%5BCima-Now.CoM%5D%20Khaled.Nour.And.His.Son.S01E12.HD-480p.mp4",
      "size": "247.75 ميجا"
    },
    {
      "name": "Episode 13",
      "url": "https://deva-cpmav9sk6x.cimanowtv.com/uploads/2024/04/05/_Cima-Now.CoM_%20Khaled.Nour.And.His.Son.S01E13.HD/%5BCima-Now.CoM%5D%20Khaled.Nour.And.His.Son.S01E13.HD-480p.mp4",
      "size": "240.77 ميجا"
    },
    {
      "name": "Episode 14",
      "url": "https://deva-cpmav9sk6x.cimanowtv.com/uploads/2024/04/06/_Cima-Now.CoM_%20Khaled.Nour.And.His.Son.S01E14.HD/%5BCima-Now.CoM%5D%20Khaled.Nour.And.His.Son.S01E14.HD-480p.mp4",
      "size": "259.52 ميجا"
    },
    {
      "name": "Episode 15",
      "url": "https://deva-cpmav9sk6x.cimanowtv.com/uploads/2024/04/07/_Cima-Now.CoM_%20Khaled.Nour.And.His.Son.S01E15.HD/%5BCima-Now.CoM%5D%20Khaled.Nour.And.His.Son.S01E15.HD-480p.mp4",
      "size": "344.85 ميجا"
    }
  ]
}