{
  "title": "[EgyFilm] 7sba 3mry S01",
  "episodes": [
    {
      "name": "Episode 01",
      "url": "https://deva-cpmav9sk6x38.cimanowtv.com/uploads/2025/03/15/_Cima-Now.CoM_%20Hesbet.Omry.S01E01.HD/%5BCima-Now.CoM%5D%20Hesbet.Omry.S01E01.HD-360p.mp4",
      "size": "177.52 ميجا"
    },
    {
      "name": "Episode 02",
      "url": "https://deva-cpmav9sk6x38.cimanowtv.com/uploads/2025/03/16/_Cima-Now.CoM_%20Hesbet.Omry.S01E02.HD/%5BCima-Now.CoM%5D%20Hesbet.Omry.S01E02.HD-360p.mp4",
      "size": "179.02 ميجا"
    },
    {
      "name": "Episode 03",
      "url": "https://deva-cpmav9sk6x38.cimanowtv.com/uploads/2025/03/17/_Cima-Now.CoM_%20Hesbet.Omry.S01E03.HD/%5BCima-Now.CoM%5D%20Hesbet.Omry.S01E03.HD-360p.mp4",
      "size": "160.21 ميجا"
    },
    {
      "name": "Episode 04",
      "url": "https://deva-cpmav9sk6x37.cimanowtv.com/uploads/2025/03/18/_Cima-Now.CoM_%20Hesbet.Omry.S01E04.HD/%5BCima-Now.CoM%5D%20Hesbet.Omry.S01E04.HD-360p.mp4",
      "size": "155.44 ميجا"
    },
    {
      "name": "Episode 05",
      "url": "https://deva-cpmav9sk6x38.cimanowtv.com/uploads/2025/03/19/_Cima-Now.CoM_%20Hesbet.Omry.S01E05.HD/%5BCima-Now.CoM%5D%20Hesbet.Omry.S01E05.HD-360p.mp4",
      "size": "113.79 ميجا"
    },
    {
      "name": "Episode 11",
      "url": "https://deva-cpmav9sk6x38.cimanowtv.com/uploads/2025/03/25/_Cima-Now.CoM_%20Hesbet.Omry.S01E11.HD/%5BCima-Now.CoM%5D%20Hesbet.Omry.S01E11.HD-360p.mp4",
      "size": "125.80 ميجا"
    },
    {
      "name": "Episode 12",
      "url": "https://deva-cpmav9sk6x37.cimanowtv.com/uploads/2025/03/26/_Cima-Now.CoM_%20Hesbet.Omry.S01E12.HD/%5BCima-Now.CoM%5D%20Hesbet.Omry.S01E12.HD-360p.mp4",
      "size": "108.26 ميجا"
    },
    {
      "name": "Episode 13",
      "url": "https://deva-cpmav9sk6x38.cimanowtv.com/uploads/2025/03/27/_Cima-Now.CoM_%20Hesbet.Omry.S01E13.HD/%5BCima-Now.CoM%5D%20Hesbet.Omry.S01E13.HD-360p.mp4",
      "size": "125.49 ميجا"
    },
    {
      "name": "Episode 14",
      "url": "https://deva-cpmav9sk6x36.cimanowtv.com/uploads/2025/03/28/_Cima-Now.CoM_%20Hesbet.Omry.S01E14.HD/%5BCima-Now.CoM%5D%20Hesbet.Omry.S01E14.HD-360p.mp4",
      "size": "107.57 ميجا"
    },
    {
      "name": "Episode 15",
      "url": "https://deva-cpmav9sk6x38.cimanowtv.com/uploads/2025/03/29/_Cima-Now.CoM_%20Hesbet.Omry.S01E15.HD/%5BCima-Now.CoM%5D%20Hesbet.Omry.S01E15.HD-360p.mp4",
      "size": "119.15 ميجا"
    }
  ]
}