{
  "title": "[EgyFilm] msar agbary S01",
  "episodes": [
    {
      "name": "Episode 01",
      "url": "https://deva-cpmav9sk6x32.cimanowtv.com/uploads/2024/03/11/_Cima-Now.CoM_%20Masar.Egbari.S01E01.HD/%5BCima-Now.CoM%5D%20Masar.Egbari.S01E01.HD-1080p.mp4",
      "size": "826.30 ميجا"
    },
    {
      "name": "Episode 02",
      "url": "https://deva-cpmav9sk6x31.cimanowtv.com/uploads/2024/03/12/_Cima-Now.CoM_%20Masar.Egbari.S01E02.HD/%5BCima-Now.CoM%5D%20Masar.Egbari.S01E02.HD-1080p.mp4",
      "size": "686.29 ميجا"
    },
    {
      "name": "Episode 03",
      "url": "https://deva-cpmav9sk6x31.cimanowtv.com/uploads/2024/03/13/_Cima-Now.CoM_%20Masar.Egbari.S01E03.HD/%5BCima-Now.CoM%5D%20Masar.Egbari.S01E03.HD-1080p.mp4",
      "size": "698.44 ميجا"
    },
    {
      "name": "Episode 04",
      "url": "https://deva-cpmav9sk6x32.cimanowtv.com/uploads/2024/03/14/_Cima-Now.CoM_%20Masar.Egbari.S01E04.HD/%5BCima-Now.CoM%5D%20Masar.Egbari.S01E04.HD-1080p.mp4",
      "size": "683.77 ميجا"
    },
    {
      "name": "Episode 05",
      "url": "https://deva-cpmav9sk6x30.cimanowtv.com/uploads/2024/03/15/_Cima-Now.CoM_%20Masar.Egbari.S01E05.HD/%5BCima-Now.CoM%5D%20Masar.Egbari.S01E05.HD-1080p.mp4",
      "size": "690.71 ميجا"
    },
    {
      "name": "Episode 06",
      "url": "https://deva-cpmav9sk6x31.cimanowtv.com/uploads/2024/03/16/_Cima-Now.CoM_%20Masar.Egbari.S01E06.HD/%5BCima-Now.CoM%5D%20Masar.Egbari.S01E06.HD-1080p.mp4",
      "size": "708.66 ميجا"
    },
    {
      "name": "Episode 07",
      "url": "https://deva-cpmav9sk6x32.cimanowtv.com/uploads/2024/03/17/_Cima-Now.CoM_%20Masar.Egbari.S01E07.HD/%5BCima-Now.CoM%5D%20Masar.Egbari.S01E07.HD-1080p.mp4",
      "size": "703.37 ميجا"
    },
    {
      "name": "Episode 08",
      "url": "https://deva-cpmav9sk6x31.cimanowtv.com/uploads/2024/03/18/_Cima-Now.CoM_%20Masar.Egbari.S01E08.HD/%5BCima-Now.CoM%5D%20Masar.Egbari.S01E08.HD-1080p.mp4",
      "size": "636.26 ميجا"
    },
    {
      "name": "Episode 09",
      "url": "https://deva-cpmav9sk6x32.cimanowtv.com/uploads/2024/03/19/_Cima-Now.CoM_%20Masar.Egbari.S01E09.HD/%5BCima-Now.CoM%5D%20Masar.Egbari.S01E09.HD-1080p.mp4",
      "size": "647.60 ميجا"
    },
    {
      "name": "Episode 10",
      "url": "https://deva-cpmav9sk6x32.cimanowtv.com/uploads/2024/03/20/_Cima-Now.CoM_%20Masar.Egbari.S01E10.HD/%5BCima-Now.CoM%5D%20Masar.Egbari.S01E10.HD-1080p.mp4",
      "size": "651.35 ميجا"
    },
    {
      "name": "Episode 11",
      "url": "https://deva-cpmav9sk6x30.cimanowtv.com/uploads/2024/03/21/_Cima-Now.CoM_%20Masar.Egbari.S01E11.HD/%5BCima-Now.CoM%5D%20Masar.Egbari.S01E11.HD-1080p.mp4",
      "size": "630.09 ميجا"
    },
    {
      "name": "Episode 12",
      "url": "https://deva-cpmav9sk6x32.cimanowtv.com/uploads/2024/03/21/_Cima-Now.CoM_%20Masar.Egbari.S01E12.HD/%5BCima-Now.CoM%5D%20Masar.Egbari.S01E12.HD-1080p.mp4",
      "size": "656.36 ميجا"
    },
    {
      "name": "Episode 13",
      "url": "https://deva-cpmav9sk6x32.cimanowtv.com/uploads/2024/03/23/_Cima-Now.CoM_%20Masar.Egbari.S01E13.HD/%5BCima-Now.CoM%5D%20Masar.Egbari.S01E13.HD-1080p.mp4",
      "size": "692.14 ميجا"
    },
    {
      "name": "Episode 14",
      "url": "https://deva-cpmav9sk6x30.cimanowtv.com/uploads/2024/03/24/_Cima-Now.CoM_%20Masar.Egbari.S01E14.HD/%5BCima-Now.CoM%5D%20Masar.Egbari.S01E14.HD-1080p.mp4",
      "size": "788.32 ميجا"
    },
    {
      "name": "Episode 15",
      "url": "https://deva-cpmav9sk6x30.cimanowtv.com/uploads/2024/03/25/_Cima-Now.CoM_%20Masar.Egbari.S01E15.HD/%5BCima-Now.CoM%5D%20Masar.Egbari.S01E15.HD-1080p.mp4",
      "size": "961.58 ميجا"
    },
    {
      "name": "Episode 16",
      "url": "https://deva-cpmav9sk6x30.cimanowtv.com/uploads/2024/03/26/_Cima-Now.CoM_%20Sayd.El.Akareb.S01E16.HD/%5BCima-Now.CoM%5D%20Sayd.El.Akareb.S01E16.HD-1080p.mp4",
      "size": "604.62 ميجا"
    },
    {
      "name": "Episode 17",
      "url": "https://deva-cpmav9sk6x30.cimanowtv.com/uploads/2024/03/27/_Cima-Now.CoM_%20Sayd.El.Akareb.S01E17.HD/%5BCima-Now.CoM%5D%20Sayd.El.Akareb.S01E17.HD-1080p.mp4",
      "size": "642.24 ميجا"
    },
    {
      "name": "Episode 18",
      "url": "https://deva-cpmav9sk6x32.cimanowtv.com/uploads/2024/03/28/_Cima-Now.CoM_%20Sayd.El.Akareb.S01E18.HD/%5BCima-Now.CoM%5D%20Sayd.El.Akareb.S01E18.HD-1080p.mp4",
      "size": "618.12 ميجا"
    },
    {
      "name": "Episode 19",
      "url": "https://deva-cpmav9sk6x32.cimanowtv.com/uploads/2024/03/29/_Cima-Now.CoM_%20Sayd.El.Akareb.S01E19.HD/%5BCima-Now.CoM%5D%20Sayd.El.Akareb.S01E19.HD-1080p.mp4",
      "size": "571.56 ميجا"
    },
    {
      "name": "Episode 20",
      "url": "https://deva-cpmav9sk6x32.cimanowtv.com/uploads/2024/03/30/_Cima-Now.CoM_%20Sayd.El.Akareb.S01E20.HD/%5BCima-Now.CoM%5D%20Sayd.El.Akareb.S01E20.HD-1080p.mp4",
      "size": "605.82 ميجا"
    },
    {
      "name": "Episode 21",
      "url": "https://deva-cpmav9sk6x31.cimanowtv.com/uploads/2024/03/31/_Cima-Now.CoM_%20Sayd.El.Akareb.S01E21.HD/%5BCima-Now.CoM%5D%20Sayd.El.Akareb.S01E21.HD-1080p.mp4",
      "size": "606.36 ميجا"
    },
    {
      "name": "Episode 22",
      "url": "https://deva-cpmav9sk6x31.cimanowtv.com/uploads/2024/04/01/_Cima-Now.CoM_%20Sayd.El.Akareb.S01E22.HD/%5BCima-Now.CoM%5D%20Sayd.El.Akareb.S01E22.HD-1080p.mp4",
      "size": "613.82 ميجا"
    },
    {
      "name": "Episode 23",
      "url": "https://deva-cpmav9sk6x32.cimanowtv.com/uploads/2024/04/02/_Cima-Now.CoM_%20Sayd.El.Akareb.S01E23.HD/%5BCima-Now.CoM%5D%20Sayd.El.Akareb.S01E23.HD-1080p.mp4",
      "size": "604.28 ميجا"
    },
    {
      "name": "Episode 24",
      "url": "https://deva-cpmav9sk6x30.cimanowtv.com/uploads/2024/04/03/_Cima-Now.CoM_%20Sayd.El.Akareb.S01E24.HD/%5BCima-Now.CoM%5D%20Sayd.El.Akareb.S01E24.HD-1080p.mp4",
      "size": "595.31 ميجا"
    },
    {
      "name": "Episode 25",
      "url": "https://deva-cpmav9sk6x32.cimanowtv.com/uploads/2024/04/04/_Cima-Now.CoM_%20Sayd.El.Akareb.S01E25.HD/%5BCima-Now.CoM%5D%20Sayd.El.Akareb.S01E25.HD-1080p.mp4",
      "size": "603.68 ميجا"
    },
    {
      "name": "Episode 26",
      "url": "https://deva-cpmav9sk6x32.cimanowtv.com/uploads/2024/04/05/_Cima-Now.CoM_%20Sayd.El.Akareb.S01E26.HD/%5BCima-Now.CoM%5D%20Sayd.El.Akareb.S01E26.HD-1080p.mp4",
      "size": "614.31 ميجا"
    },
    {
      "name": "Episode 27",
      "url": "https://deva-cpmav9sk6x.cimanowtv.com/uploads/2024/04/06/_Cima-Now.CoM_%20Sayd.El.Akareb.S01E27.HD/%5BCima-Now.CoM%5D%20Sayd.El.Akareb.S01E27.HD-1080p.mp4",
      "size": "613.20 ميجا"
    },
    {
      "name": "Episode 28",
      "url": "https://deva-cpmav9sk6x32.cimanowtv.com/uploads/2024/04/07/_Cima-Now.CoM_%20Sayd.El.Akareb.S01E28.HD/%5BCima-Now.CoM%5D%20Sayd.El.Akareb.S01E28.HD-1080p.mp4",
      "size": "618.13 ميجا"
    },
    {
      "name": "Episode 29",
      "url": "https://deva-cpmav9sk6x32.cimanowtv.com/uploads/2024/04/08/_Cima-Now.CoM_%20Sayd.El.Akareb.S01E29.HD/%5BCima-Now.CoM%5D%20Sayd.El.Akareb.S01E29.HD-1080p.mp4",
      "size": "571.75 ميجا"
    },
    {
      "name": "Episode 30",
      "url": "https://deva-cpmav9sk6x.cimanowtv.com/uploads/2024/04/09/_Cima-Now.CoM_%20Sayd.El.Akareb.S01E30.HD/%5BCima-Now.CoM%5D%20Sayd.El.Akareb.S01E30.HD-1080p.mp4",
      "size": "738.73 ميجا"
    }
  ]
}