{
  "title": "[EgyFilm] msar agbary S01",
  "episodes": [
    {
      "name": "Episode 05",
      "url": "https://vk.com/doc846471716_672167364",
      "size": "135.27 ميجا"
    },
    {
      "name": "Episode 06",
      "url": "https://vk.com/doc846471716_672203257",
      "size": "138.92 ميجا"
    },
    {
      "name": "Episode 07",
      "url": "https://vk.com/doc854075720_675256117",
      "size": "140.00 ميجا"
    },
    {
      "name": "Episode 08",
      "url": "https://vk.com/doc854075720_675292608",
      "size": "130.16 ميجا"
    },
    {
      "name": "Episode 09",
      "url": "https://vk.com/doc854075720_675326466",
      "size": "129.73 ميجا"
    },
    {
      "name": "Episode 10",
      "url": "https://vk.com/doc854075720_675362766",
      "size": "139.30 ميجا"
    },
    {
      "name": "Episode 11",
      "url": "https://vk.com/doc854075720_675398839",
      "size": "125.91 ميجا"
    },
    {
      "name": "Episode 12",
      "url": "https://vk.com/doc846471716_672387635",
      "size": "138.37 ميجا"
    },
    {
      "name": "Episode 13",
      "url": "https://vk.com/doc854075720_675468975",
      "size": "146.29 ميجا"
    },
    {
      "name": "Episode 15",
      "url": "https://vk.com/doc854075720_675522771",
      "size": "201.09 ميجا"
    }
  ]
}