{
  "title": "[EgyFilm] brkat S01",
  "episodes": [
    {
      "name": "Episode 01",
      "url": "https://deva-cpmav9sk6x4.cimanowtv.com/uploads/2020/08/07/_Cima-Now.CoM_%20Barakat.S01E01.HD/%5BCima-Now.CoM%5D%20Barakat.S01E01.HD-720p.mp4",
      "size": "464.92 ميجا"
    },
    {
      "name": "Episode 02",
      "url": "https://deva-cpmav9sk6x4.cimanowtv.com/uploads/2020/08/07/_Cima-Now.CoM_%20Barakat.S01E02.HD/%5BCima-Now.CoM%5D%20Barakat.S01E02.HD-720p.mp4",
      "size": "433.70 ميجا"
    },
    {
      "name": "Episode 03",
      "url": "https://deva-cpmav9sk6x4.cimanowtv.com/uploads/2020/08/07/_Cima-Now.CoM_%20Barakat.S01E03.HD/%5BCima-Now.CoM%5D%20Barakat.S01E03.HD-720p.mp4",
      "size": "392.99 ميجا"
    },
    {
      "name": "Episode 04",
      "url": "https://deva-cpmav9sk6x4.cimanowtv.com/uploads/2020/08/07/_Cima-Now.CoM_%20Barakat.S01E04.HD/%5BCima-Now.CoM%5D%20Barakat.S01E04.HD-720p.mp4",
      "size": "446.51 ميجا"
    },
    {
      "name": "Episode 05",
      "url": "https://deva-cpmav9sk6x4.cimanowtv.com/uploads/2020/08/07/_Cima-Now.CoM_%20Barakat.S01E05.HD/%5BCima-Now.CoM%5D%20Barakat.S01E05.HD-720p.mp4",
      "size": "428.78 ميجا"
    },
    {
      "name": "Episode 06",
      "url": "https://deva-cpmav9sk6x4.cimanowtv.com/uploads/2020/08/07/_Cima-Now.CoM_%20Barakat.S01E06.HD/%5BCima-Now.CoM%5D%20Barakat.S01E06.HD-720p.mp4",
      "size": "458.26 ميجا"
    },
    {
      "name": "Episode 07",
      "url": "https://deva-cpmav9sk6x4.cimanowtv.com/uploads/2020/08/07/_Cima-Now.CoM_%20Barakat.S01E07.Final.HD/%5BCima-Now.CoM%5D%20Barakat.S01E07.Final.HD-720p.mp4",
      "size": "435.88 ميجا"
    }
  ]
}